Workbook

Sheet 1_Bang_Xac_Suat_Thang
A1: Mã Bộ | B1: Tên Bộ Thuật Toán | C1: Tổng Tín Hiệu Chuẩn | D1: Đã Phân Định | E1: Lệnh THẮNG | F1: Lệnh THUA | G1: Win Rate T+3 (Hàng Về) | H1: Win Rate Tổng (%) | I1: Lãi TB Lệnh Thắng (Avg Win) | J1: Lỗ TB Lệnh Thua (Avg Loss) | K1: Tỷ Lệ R:R (Payoff Ratio) | L1: Profit Factor (Tổng Lãi/Lỗ) | M1: Kỳ Vọng Toán Học (Expectancy) | N1: Alpha TB vs VNINDEX | O1: Đánh Giá Chuẩn Quỹ Định Lượng
A2: ALGO_01 | B2: 🔥 BỘ 01: BÙNG NỔ DÒNG TIỀN & VƯỢT NỀN (CANSLIM BREAKOUT) | C2: =COUNTIF('2_Nhat_Ky_Theo_Doi_Tuong_Lai'!$B$2:$B$1000, A2) | D2: =E2+F2 | E2: =COUNTIFS('2_Nhat_Ky_Theo_Doi_Tuong_Lai'!$B$2:$B$1000, A2, '2_Nhat_Ky_Theo_Doi_Tuong_Lai'!$AF$2:$AF$1000, "THẮNG") | F2: =COUNTIFS('2_Nhat_Ky_Theo_Doi_Tuong_Lai'!$B$2:$B$1000, A2, '2_Nhat_Ky_Theo_Doi_Tuong_Lai'!$AF$2:$AF$1000, "THUA") | G2: =IFERROR(COUNTIFS('2_Nhat_Ky_Theo_Doi_Tuong_Lai'!$B$2:$B$1000, A2, '2_Nhat_Ky_Theo_Doi_Tuong_Lai'!$AE$2:$AE$1000, "THẮNG")/COUNTIFS('2_Nhat_Ky_Theo_Doi_Tuong_Lai'!$B$2:$B$1000, A2, '2_Nhat_Ky_Theo_Doi_Tuong_Lai'!$AE$2:$AE$1000, "<>CHỜ T+3"), 0) | H2: =IF(D2>0, E2/D2, 0) | I2: =IFERROR(AVERAGEIFS('2_Nhat_Ky_Theo_Doi_Tuong_Lai'!$AA$2:$AA$1000, '2_Nhat_Ky_Theo_Doi_Tuong_Lai'!$B$2:$B$1000, A2, '2_Nhat_Ky_Theo_Doi_Tuong_Lai'!$AF$2:$AF$1000, "THẮNG"), 0) | J2: =IFERROR(AVERAGEIFS('2_Nhat_Ky_Theo_Doi_Tuong_Lai'!$AA$2:$AA$1000, '2_Nhat_Ky_Theo_Doi_Tuong_Lai'!$B$2:$B$1000, A2, '2_Nhat_Ky_Theo_Doi_Tuong_Lai'!$AF$2:$AF$1000, "THUA"), 0) | K2: =IF(AND(F2>0, ABS(J2)>0), I2/ABS(J2), IF(E2>0, 5.0, 0)) | L2: =IF(ABS(SUMIFS('2_Nhat_Ky_Theo_Doi_Tuong_Lai'!$AA$2:$AA$1000, '2_Nhat_Ky_Theo_Doi_Tuong_Lai'!$B$2:$B$1000, A2, '2_Nhat_Ky_Theo_Doi_Tuong_Lai'!$AF$2:$AF$1000, "THUA"))>0, SUMIFS('2_Nhat_Ky_Theo_Doi_Tuong_Lai'!$AA$2:$AA$1000, '2_Nhat_Ky_Theo_Doi_Tuong_Lai'!$B$2:$B$1000, A2, '2_Nhat_Ky_Theo_Doi_Tuong_Lai'!$AF$2:$AF$1000, "THẮNG")/ABS(SUMIFS('2_Nhat_Ky_Theo_Doi_Tuong_Lai'!$AA$2:$AA$1000, '2_Nhat_Ky_Theo_Doi_Tuong_Lai'!$B$2:$B$1000, A2, '2_Nhat_Ky_Theo_Doi_Tuong_Lai'!$AF$2:$AF$1000, "THUA")), IF(E2>0, 5.0, 0)) | M2: =IF(D2>0, (H2*I2)+((1-H2)*J2), 0) | N2: =IFERROR(AVERAGEIFS('2_Nhat_Ky_Theo_Doi_Tuong_Lai'!$AB$2:$AB$1000, '2_Nhat_Ky_Theo_Doi_Tuong_Lai'!$B$2:$B$1000, A2, '2_Nhat_Ky_Theo_Doi_Tuong_Lai'!$AF$2:$AF$1000, "<>ĐANG CHỜ"), 0) | O2: =IF(D2=0, "⏳ Đang chờ T+1 -> T+3", IF(AND(M2>=0.015, L2>=1.5), "🏆 CHÉN THÁNH (Giải ngân Lớn)", IF(M2>0, "🟢 KỲ VỌNG DƯƠNG (Có Lợi Thế)", "🔴 KỲ VỌNG ÂM (Tạm Ngưng)")))
A3: ALGO_02 | B3: 🛡️ BỘ 02: GOM NỀN TÍCH LŨY SIẾT BIÊN ĐỘ VCP (SEPA ACCUMULATION) | C3: =COUNTIF('2_Nhat_Ky_Theo_Doi_Tuong_Lai'!$B$2:$B$1000, A3) | D3: =E3+F3 | E3: =COUNTIFS('2_Nhat_Ky_Theo_Doi_Tuong_Lai'!$B$2:$B$1000, A3, '2_Nhat_Ky_Theo_Doi_Tuong_Lai'!$AF$2:$AF$1000, "THẮNG") | F3: =COUNTIFS('2_Nhat_Ky_Theo_Doi_Tuong_Lai'!$B$2:$B$1000, A3, '2_Nhat_Ky_Theo_Doi_Tuong_Lai'!$AF$2:$AF$1000, "THUA") | G3: =IFERROR(COUNTIFS('2_Nhat_Ky_Theo_Doi_Tuong_Lai'!$B$2:$B$1000, A3, '2_Nhat_Ky_Theo_Doi_Tuong_Lai'!$AE$2:$AE$1000, "THẮNG")/COUNTIFS('2_Nhat_Ky_Theo_Doi_Tuong_Lai'!$B$2:$B$1000, A3, '2_Nhat_Ky_Theo_Doi_Tuong_Lai'!$AE$2:$AE$1000, "<>CHỜ T+3"), 0) | H3: =IF(D3>0, E3/D3, 0) | I3: =IFERROR(AVERAGEIFS('2_Nhat_Ky_Theo_Doi_Tuong_Lai'!$AA$2:$AA$1000, '2_Nhat_Ky_Theo_Doi_Tuong_Lai'!$B$2:$B$1000, A3, '2_Nhat_Ky_Theo_Doi_Tuong_Lai'!$AF$2:$AF$1000, "THẮNG"), 0) | J3: =IFERROR(AVERAGEIFS('2_Nhat_Ky_Theo_Doi_Tuong_Lai'!$AA$2:$AA$1000, '2_Nhat_Ky_Theo_Doi_Tuong_Lai'!$B$2:$B$1000, A3, '2_Nhat_Ky_Theo_Doi_Tuong_Lai'!$AF$2:$AF$1000, "THUA"), 0) | K3: =IF(AND(F3>0, ABS(J3)>0), I3/ABS(J3), IF(E3>0, 5.0, 0)) | L3: =IF(ABS(SUMIFS('2_Nhat_Ky_Theo_Doi_Tuong_Lai'!$AA$2:$AA$1000, '2_Nhat_Ky_Theo_Doi_Tuong_Lai'!$B$2:$B$1000, A3, '2_Nhat_Ky_Theo_Doi_Tuong_Lai'!$AF$2:$AF$1000, "THUA"))>0, SUMIFS('2_Nhat_Ky_Theo_Doi_Tuong_Lai'!$AA$2:$AA$1000, '2_Nhat_Ky_Theo_Doi_Tuong_Lai'!$B$2:$B$1000, A3, '2_Nhat_Ky_Theo_Doi_Tuong_Lai'!$AF$2:$AF$1000, "THẮNG")/ABS(SUMIFS('2_Nhat_Ky_Theo_Doi_Tuong_Lai'!$AA$2:$AA$1000, '2_Nhat_Ky_Theo_Doi_Tuong_Lai'!$B$2:$B$1000, A3, '2_Nhat_Ky_Theo_Doi_Tuong_Lai'!$AF$2:$AF$1000, "THUA")), IF(E3>0, 5.0, 0)) | M3: =IF(D3>0, (H3*I3)+((1-H3)*J3), 0) | N3: =IFERROR(AVERAGEIFS('2_Nhat_Ky_Theo_Doi_Tuong_Lai'!$AB$2:$AB$1000, '2_Nhat_Ky_Theo_Doi_Tuong_Lai'!$B$2:$B$1000, A3, '2_Nhat_Ky_Theo_Doi_Tuong_Lai'!$AF$2:$AF$1000, "<>ĐANG CHỜ"), 0) | O3: =IF(D3=0, "⏳ Đang chờ T+1 -> T+3", IF(AND(M3>=0.015, L3>=1.5), "🏆 CHÉN THÁNH (Giải ngân Lớn)", IF(M3>0, "🟢 KỲ VỌNG DƯƠNG (Có Lợi Thế)", "🔴 KỲ VỌNG ÂM (Tạm Ngưng)")))
A4: ALGO_03 | B4: ⚡ BỘ 03: BẮT ĐÁY RÚT CHÂN & ĐẢO CHIỀU QUÁ BÁN (WYCKOFF SPRING) | C4: =COUNTIF('2_Nhat_Ky_Theo_Doi_Tuong_Lai'!$B$2:$B$1000, A4) | D4: =E4+F4 | E4: =COUNTIFS('2_Nhat_Ky_Theo_Doi_Tuong_Lai'!$B$2:$B$1000, A4, '2_Nhat_Ky_Theo_Doi_Tuong_Lai'!$AF$2:$AF$1000, "THẮNG") | F4: =COUNTIFS('2_Nhat_Ky_Theo_Doi_Tuong_Lai'!$B$2:$B$1000, A4, '2_Nhat_Ky_Theo_Doi_Tuong_Lai'!$AF$2:$AF$1000, "THUA") | G4: =IFERROR(COUNTIFS('2_Nhat_Ky_Theo_Doi_Tuong_Lai'!$B$2:$B$1000, A4, '2_Nhat_Ky_Theo_Doi_Tuong_Lai'!$AE$2:$AE$1000, "THẮNG")/COUNTIFS('2_Nhat_Ky_Theo_Doi_Tuong_Lai'!$B$2:$B$1000, A4, '2_Nhat_Ky_Theo_Doi_Tuong_Lai'!$AE$2:$AE$1000, "<>CHỜ T+3"), 0) | H4: =IF(D4>0, E4/D4, 0) | I4: =IFERROR(AVERAGEIFS('2_Nhat_Ky_Theo_Doi_Tuong_Lai'!$AA$2:$AA$1000, '2_Nhat_Ky_Theo_Doi_Tuong_Lai'!$B$2:$B$1000, A4, '2_Nhat_Ky_Theo_Doi_Tuong_Lai'!$AF$2:$AF$1000, "THẮNG"), 0) | J4: =IFERROR(AVERAGEIFS('2_Nhat_Ky_Theo_Doi_Tuong_Lai'!$AA$2:$AA$1000, '2_Nhat_Ky_Theo_Doi_Tuong_Lai'!$B$2:$B$1000, A4, '2_Nhat_Ky_Theo_Doi_Tuong_Lai'!$AF$2:$AF$1000, "THUA"), 0) | K4: =IF(AND(F4>0, ABS(J4)>0), I4/ABS(J4), IF(E4>0, 5.0, 0)) | L4: =IF(ABS(SUMIFS('2_Nhat_Ky_Theo_Doi_Tuong_Lai'!$AA$2:$AA$1000, '2_Nhat_Ky_Theo_Doi_Tuong_Lai'!$B$2:$B$1000, A4, '2_Nhat_Ky_Theo_Doi_Tuong_Lai'!$AF$2:$AF$1000, "THUA"))>0, SUMIFS('2_Nhat_Ky_Theo_Doi_Tuong_Lai'!$AA$2:$AA$1000, '2_Nhat_Ky_Theo_Doi_Tuong_Lai'!$B$2:$B$1000, A4, '2_Nhat_Ky_Theo_Doi_Tuong_Lai'!$AF$2:$AF$1000, "THẮNG")/ABS(SUMIFS('2_Nhat_Ky_Theo_Doi_Tuong_Lai'!$AA$2:$AA$1000, '2_Nhat_Ky_Theo_Doi_Tuong_Lai'!$B$2:$B$1000, A4, '2_Nhat_Ky_Theo_Doi_Tuong_Lai'!$AF$2:$AF$1000, "THUA")), IF(E4>0, 5.0, 0)) | M4: =IF(D4>0, (H4*I4)+((1-H4)*J4), 0) | N4: =IFERROR(AVERAGEIFS('2_Nhat_Ky_Theo_Doi_Tuong_Lai'!$AB$2:$AB$1000, '2_Nhat_Ky_Theo_Doi_Tuong_Lai'!$B$2:$B$1000, A4, '2_Nhat_Ky_Theo_Doi_Tuong_Lai'!$AF$2:$AF$1000, "<>ĐANG CHỜ"), 0) | O4: =IF(D4=0, "⏳ Đang chờ T+1 -> T+3", IF(AND(M4>=0.015, L4>=1.5), "🏆 CHÉN THÁNH (Giải ngân Lớn)", IF(M4>0, "🟢 KỲ VỌNG DƯƠNG (Có Lợi Thế)", "🔴 KỲ VỌNG ÂM (Tạm Ngưng)")))
A5: ALGO_04 | B5: 👑 BỘ 04: SIÊU CỔ PHIẾU KHÁNG BÃO & ĐỈNH 52W (RS ALPHA LEADER) | C5: =COUNTIF('2_Nhat_Ky_Theo_Doi_Tuong_Lai'!$B$2:$B$1000, A5) | D5: =E5+F5 | E5: =COUNTIFS('2_Nhat_Ky_Theo_Doi_Tuong_Lai'!$B$2:$B$1000, A5, '2_Nhat_Ky_Theo_Doi_Tuong_Lai'!$AF$2:$AF$1000, "THẮNG") | F5: =COUNTIFS('2_Nhat_Ky_Theo_Doi_Tuong_Lai'!$B$2:$B$1000, A5, '2_Nhat_Ky_Theo_Doi_Tuong_Lai'!$AF$2:$AF$1000, "THUA") | G5: =IFERROR(COUNTIFS('2_Nhat_Ky_Theo_Doi_Tuong_Lai'!$B$2:$B$1000, A5, '2_Nhat_Ky_Theo_Doi_Tuong_Lai'!$AE$2:$AE$1000, "THẮNG")/COUNTIFS('2_Nhat_Ky_Theo_Doi_Tuong_Lai'!$B$2:$B$1000, A5, '2_Nhat_Ky_Theo_Doi_Tuong_Lai'!$AE$2:$AE$1000, "<>CHỜ T+3"), 0) | H5: =IF(D5>0, E5/D5, 0) | I5: =IFERROR(AVERAGEIFS('2_Nhat_Ky_Theo_Doi_Tuong_Lai'!$AA$2:$AA$1000, '2_Nhat_Ky_Theo_Doi_Tuong_Lai'!$B$2:$B$1000, A5, '2_Nhat_Ky_Theo_Doi_Tuong_Lai'!$AF$2:$AF$1000, "THẮNG"), 0) | J5: =IFERROR(AVERAGEIFS('2_Nhat_Ky_Theo_Doi_Tuong_Lai'!$AA$2:$AA$1000, '2_Nhat_Ky_Theo_Doi_Tuong_Lai'!$B$2:$B$1000, A5, '2_Nhat_Ky_Theo_Doi_Tuong_Lai'!$AF$2:$AF$1000, "THUA"), 0) | K5: =IF(AND(F5>0, ABS(J5)>0), I5/ABS(J5), IF(E5>0, 5.0, 0)) | L5: =IF(ABS(SUMIFS('2_Nhat_Ky_Theo_Doi_Tuong_Lai'!$AA$2:$AA$1000, '2_Nhat_Ky_Theo_Doi_Tuong_Lai'!$B$2:$B$1000, A5, '2_Nhat_Ky_Theo_Doi_Tuong_Lai'!$AF$2:$AF$1000, "THUA"))>0, SUMIFS('2_Nhat_Ky_Theo_Doi_Tuong_Lai'!$AA$2:$AA$1000, '2_Nhat_Ky_Theo_Doi_Tuong_Lai'!$B$2:$B$1000, A5, '2_Nhat_Ky_Theo_Doi_Tuong_Lai'!$AF$2:$AF$1000, "THẮNG")/ABS(SUMIFS('2_Nhat_Ky_Theo_Doi_Tuong_Lai'!$AA$2:$AA$1000, '2_Nhat_Ky_Theo_Doi_Tuong_Lai'!$B$2:$B$1000, A5, '2_Nhat_Ky_Theo_Doi_Tuong_Lai'!$AF$2:$AF$1000, "THUA")), IF(E5>0, 5.0, 0)) | M5: =IF(D5>0, (H5*I5)+((1-H5)*J5), 0) | N5: =IFERROR(AVERAGEIFS('2_Nhat_Ky_Theo_Doi_Tuong_Lai'!$AB$2:$AB$1000, '2_Nhat_Ky_Theo_Doi_Tuong_Lai'!$B$2:$B$1000, A5, '2_Nhat_Ky_Theo_Doi_Tuong_Lai'!$AF$2:$AF$1000, "<>ĐANG CHỜ"), 0) | O5: =IF(D5=0, "⏳ Đang chờ T+1 -> T+3", IF(AND(M5>=0.015, L5>=1.5), "🏆 CHÉN THÁNH (Giải ngân Lớn)", IF(M5>0, "🟢 KỲ VỌNG DƯƠNG (Có Lợi Thế)", "🔴 KỲ VỌNG ÂM (Tạm Ngưng)")))
A6: ALGO_05 | B6: 🎯 BỘ 05: ĐIỂM MUA KÉO NGƯỢC HỖ TRỢ NGẮN HẠN (MA20 PULLBACK) | C6: =COUNTIF('2_Nhat_Ky_Theo_Doi_Tuong_Lai'!$B$2:$B$1000, A6) | D6: =E6+F6 | E6: =COUNTIFS('2_Nhat_Ky_Theo_Doi_Tuong_Lai'!$B$2:$B$1000, A6, '2_Nhat_Ky_Theo_Doi_Tuong_Lai'!$AF$2:$AF$1000, "THẮNG") | F6: =COUNTIFS('2_Nhat_Ky_Theo_Doi_Tuong_Lai'!$B$2:$B$1000, A6, '2_Nhat_Ky_Theo_Doi_Tuong_Lai'!$AF$2:$AF$1000, "THUA") | G6: =IFERROR(COUNTIFS('2_Nhat_Ky_Theo_Doi_Tuong_Lai'!$B$2:$B$1000, A6, '2_Nhat_Ky_Theo_Doi_Tuong_Lai'!$AE$2:$AE$1000, "THẮNG")/COUNTIFS('2_Nhat_Ky_Theo_Doi_Tuong_Lai'!$B$2:$B$1000, A6, '2_Nhat_Ky_Theo_Doi_Tuong_Lai'!$AE$2:$AE$1000, "<>CHỜ T+3"), 0) | H6: =IF(D6>0, E6/D6, 0) | I6: =IFERROR(AVERAGEIFS('2_Nhat_Ky_Theo_Doi_Tuong_Lai'!$AA$2:$AA$1000, '2_Nhat_Ky_Theo_Doi_Tuong_Lai'!$B$2:$B$1000, A6, '2_Nhat_Ky_Theo_Doi_Tuong_Lai'!$AF$2:$AF$1000, "THẮNG"), 0) | J6: =IFERROR(AVERAGEIFS('2_Nhat_Ky_Theo_Doi_Tuong_Lai'!$AA$2:$AA$1000, '2_Nhat_Ky_Theo_Doi_Tuong_Lai'!$B$2:$B$1000, A6, '2_Nhat_Ky_Theo_Doi_Tuong_Lai'!$AF$2:$AF$1000, "THUA"), 0) | K6: =IF(AND(F6>0, ABS(J6)>0), I6/ABS(J6), IF(E6>0, 5.0, 0)) | L6: =IF(ABS(SUMIFS('2_Nhat_Ky_Theo_Doi_Tuong_Lai'!$AA$2:$AA$1000, '2_Nhat_Ky_Theo_Doi_Tuong_Lai'!$B$2:$B$1000, A6, '2_Nhat_Ky_Theo_Doi_Tuong_Lai'!$AF$2:$AF$1000, "THUA"))>0, SUMIFS('2_Nhat_Ky_Theo_Doi_Tuong_Lai'!$AA$2:$AA$1000, '2_Nhat_Ky_Theo_Doi_Tuong_Lai'!$B$2:$B$1000, A6, '2_Nhat_Ky_Theo_Doi_Tuong_Lai'!$AF$2:$AF$1000, "THẮNG")/ABS(SUMIFS('2_Nhat_Ky_Theo_Doi_Tuong_Lai'!$AA$2:$AA$1000, '2_Nhat_Ky_Theo_Doi_Tuong_Lai'!$B$2:$B$1000, A6, '2_Nhat_Ky_Theo_Doi_Tuong_Lai'!$AF$2:$AF$1000, "THUA")), IF(E6>0, 5.0, 0)) | M6: =IF(D6>0, (H6*I6)+((1-H6)*J6), 0) | N6: =IFERROR(AVERAGEIFS('2_Nhat_Ky_Theo_Doi_Tuong_Lai'!$AB$2:$AB$1000, '2_Nhat_Ky_Theo_Doi_Tuong_Lai'!$B$2:$B$1000, A6, '2_Nhat_Ky_Theo_Doi_Tuong_Lai'!$AF$2:$AF$1000, "<>ĐANG CHỜ"), 0) | O6: =IF(D6=0, "⏳ Đang chờ T+1 -> T+3", IF(AND(M6>=0.015, L6>=1.5), "🏆 CHÉN THÁNH (Giải ngân Lớn)", IF(M6>0, "🟢 KỲ VỌNG DƯƠNG (Có Lợi Thế)", "🔴 KỲ VỌNG ÂM (Tạm Ngưng)")))
A7: ALGO_06 | B7: 📈 BỘ 06: ĐỒNG THUẬN ĐỘNG LƯỢNG MACD & XU HƯỚNG ADX (TREND) | C7: =COUNTIF('2_Nhat_Ky_Theo_Doi_Tuong_Lai'!$B$2:$B$1000, A7) | D7: =E7+F7 | E7: =COUNTIFS('2_Nhat_Ky_Theo_Doi_Tuong_Lai'!$B$2:$B$1000, A7, '2_Nhat_Ky_Theo_Doi_Tuong_Lai'!$AF$2:$AF$1000, "THẮNG") | F7: =COUNTIFS('2_Nhat_Ky_Theo_Doi_Tuong_Lai'!$B$2:$B$1000, A7, '2_Nhat_Ky_Theo_Doi_Tuong_Lai'!$AF$2:$AF$1000, "THUA") | G7: =IFERROR(COUNTIFS('2_Nhat_Ky_Theo_Doi_Tuong_Lai'!$B$2:$B$1000, A7, '2_Nhat_Ky_Theo_Doi_Tuong_Lai'!$AE$2:$AE$1000, "THẮNG")/COUNTIFS('2_Nhat_Ky_Theo_Doi_Tuong_Lai'!$B$2:$B$1000, A7, '2_Nhat_Ky_Theo_Doi_Tuong_Lai'!$AE$2:$AE$1000, "<>CHỜ T+3"), 0) | H7: =IF(D7>0, E7/D7, 0) | I7: =IFERROR(AVERAGEIFS('2_Nhat_Ky_Theo_Doi_Tuong_Lai'!$AA$2:$AA$1000, '2_Nhat_Ky_Theo_Doi_Tuong_Lai'!$B$2:$B$1000, A7, '2_Nhat_Ky_Theo_Doi_Tuong_Lai'!$AF$2:$AF$1000, "THẮNG"), 0) | J7: =IFERROR(AVERAGEIFS('2_Nhat_Ky_Theo_Doi_Tuong_Lai'!$AA$2:$AA$1000, '2_Nhat_Ky_Theo_Doi_Tuong_Lai'!$B$2:$B$1000, A7, '2_Nhat_Ky_Theo_Doi_Tuong_Lai'!$AF$2:$AF$1000, "THUA"), 0) | K7: =IF(AND(F7>0, ABS(J7)>0), I7/ABS(J7), IF(E7>0, 5.0, 0)) | L7: =IF(ABS(SUMIFS('2_Nhat_Ky_Theo_Doi_Tuong_Lai'!$AA$2:$AA$1000, '2_Nhat_Ky_Theo_Doi_Tuong_Lai'!$B$2:$B$1000, A7, '2_Nhat_Ky_Theo_Doi_Tuong_Lai'!$AF$2:$AF$1000, "THUA"))>0, SUMIFS('2_Nhat_Ky_Theo_Doi_Tuong_Lai'!$AA$2:$AA$1000, '2_Nhat_Ky_Theo_Doi_Tuong_Lai'!$B$2:$B$1000, A7, '2_Nhat_Ky_Theo_Doi_Tuong_Lai'!$AF$2:$AF$1000, "THẮNG")/ABS(SUMIFS('2_Nhat_Ky_Theo_Doi_Tuong_Lai'!$AA$2:$AA$1000, '2_Nhat_Ky_Theo_Doi_Tuong_Lai'!$B$2:$B$1000, A7, '2_Nhat_Ky_Theo_Doi_Tuong_Lai'!$AF$2:$AF$1000, "THUA")), IF(E7>0, 5.0, 0)) | M7: =IF(D7>0, (H7*I7)+((1-H7)*J7), 0) | N7: =IFERROR(AVERAGEIFS('2_Nhat_Ky_Theo_Doi_Tuong_Lai'!$AB$2:$AB$1000, '2_Nhat_Ky_Theo_Doi_Tuong_Lai'!$B$2:$B$1000, A7, '2_Nhat_Ky_Theo_Doi_Tuong_Lai'!$AF$2:$AF$1000, "<>ĐANG CHỜ"), 0) | O7: =IF(D7=0, "⏳ Đang chờ T+1 -> T+3", IF(AND(M7>=0.015, L7>=1.5), "🏆 CHÉN THÁNH (Giải ngân Lớn)", IF(M7>0, "🟢 KỲ VỌNG DƯƠNG (Có Lợi Thế)", "🔴 KỲ VỌNG ÂM (Tạm Ngưng)")))
A8: ALGO_07 | B8: 🍾 BỘ 07: NÉN CHẶT CỔ CHAI & BUNG NÚT BOLLINGER (BB SQUEEZE) | C8: =COUNTIF('2_Nhat_Ky_Theo_Doi_Tuong_Lai'!$B$2:$B$1000, A8) | D8: =E8+F8 | E8: =COUNTIFS('2_Nhat_Ky_Theo_Doi_Tuong_Lai'!$B$2:$B$1000, A8, '2_Nhat_Ky_Theo_Doi_Tuong_Lai'!$AF$2:$AF$1000, "THẮNG") | F8: =COUNTIFS('2_Nhat_Ky_Theo_Doi_Tuong_Lai'!$B$2:$B$1000, A8, '2_Nhat_Ky_Theo_Doi_Tuong_Lai'!$AF$2:$AF$1000, "THUA") | G8: =IFERROR(COUNTIFS('2_Nhat_Ky_Theo_Doi_Tuong_Lai'!$B$2:$B$1000, A8, '2_Nhat_Ky_Theo_Doi_Tuong_Lai'!$AE$2:$AE$1000, "THẮNG")/COUNTIFS('2_Nhat_Ky_Theo_Doi_Tuong_Lai'!$B$2:$B$1000, A8, '2_Nhat_Ky_Theo_Doi_Tuong_Lai'!$AE$2:$AE$1000, "<>CHỜ T+3"), 0) | H8: =IF(D8>0, E8/D8, 0) | I8: =IFERROR(AVERAGEIFS('2_Nhat_Ky_Theo_Doi_Tuong_Lai'!$AA$2:$AA$1000, '2_Nhat_Ky_Theo_Doi_Tuong_Lai'!$B$2:$B$1000, A8, '2_Nhat_Ky_Theo_Doi_Tuong_Lai'!$AF$2:$AF$1000, "THẮNG"), 0) | J8: =IFERROR(AVERAGEIFS('2_Nhat_Ky_Theo_Doi_Tuong_Lai'!$AA$2:$AA$1000, '2_Nhat_Ky_Theo_Doi_Tuong_Lai'!$B$2:$B$1000, A8, '2_Nhat_Ky_Theo_Doi_Tuong_Lai'!$AF$2:$AF$1000, "THUA"), 0) | K8: =IF(AND(F8>0, ABS(J8)>0), I8/ABS(J8), IF(E8>0, 5.0, 0)) | L8: =IF(ABS(SUMIFS('2_Nhat_Ky_Theo_Doi_Tuong_Lai'!$AA$2:$AA$1000, '2_Nhat_Ky_Theo_Doi_Tuong_Lai'!$B$2:$B$1000, A8, '2_Nhat_Ky_Theo_Doi_Tuong_Lai'!$AF$2:$AF$1000, "THUA"))>0, SUMIFS('2_Nhat_Ky_Theo_Doi_Tuong_Lai'!$AA$2:$AA$1000, '2_Nhat_Ky_Theo_Doi_Tuong_Lai'!$B$2:$B$1000, A8, '2_Nhat_Ky_Theo_Doi_Tuong_Lai'!$AF$2:$AF$1000, "THẮNG")/ABS(SUMIFS('2_Nhat_Ky_Theo_Doi_Tuong_Lai'!$AA$2:$AA$1000, '2_Nhat_Ky_Theo_Doi_Tuong_Lai'!$B$2:$B$1000, A8, '2_Nhat_Ky_Theo_Doi_Tuong_Lai'!$AF$2:$AF$1000, "THUA")), IF(E8>0, 5.0, 0)) | M8: =IF(D8>0, (H8*I8)+((1-H8)*J8), 0) | N8: =IFERROR(AVERAGEIFS('2_Nhat_Ky_Theo_Doi_Tuong_Lai'!$AB$2:$AB$1000, '2_Nhat_Ky_Theo_Doi_Tuong_Lai'!$B$2:$B$1000, A8, '2_Nhat_Ky_Theo_Doi_Tuong_Lai'!$AF$2:$AF$1000, "<>ĐANG CHỜ"), 0) | O8: =IF(D8=0, "⏳ Đang chờ T+1 -> T+3", IF(AND(M8>=0.015, L8>=1.5), "🏆 CHÉN THÁNH (Giải ngân Lớn)", IF(M8>0, "🟢 KỲ VỌNG DƯƠNG (Có Lợi Thế)", "🔴 KỲ VỌNG ÂM (Tạm Ngưng)")))
A9: ALGO_08 | B9: 🐳 BỘ 08: DÒNG TIỀN CÁ MẬP GOM NGẦM THANH KHOẢN LỚN (STEALTH) | C9: =COUNTIF('2_Nhat_Ky_Theo_Doi_Tuong_Lai'!$B$2:$B$1000, A9) | D9: =E9+F9 | E9: =COUNTIFS('2_Nhat_Ky_Theo_Doi_Tuong_Lai'!$B$2:$B$1000, A9, '2_Nhat_Ky_Theo_Doi_Tuong_Lai'!$AF$2:$AF$1000, "THẮNG") | F9: =COUNTIFS('2_Nhat_Ky_Theo_Doi_Tuong_Lai'!$B$2:$B$1000, A9, '2_Nhat_Ky_Theo_Doi_Tuong_Lai'!$AF$2:$AF$1000, "THUA") | G9: =IFERROR(COUNTIFS('2_Nhat_Ky_Theo_Doi_Tuong_Lai'!$B$2:$B$1000, A9, '2_Nhat_Ky_Theo_Doi_Tuong_Lai'!$AE$2:$AE$1000, "THẮNG")/COUNTIFS('2_Nhat_Ky_Theo_Doi_Tuong_Lai'!$B$2:$B$1000, A9, '2_Nhat_Ky_Theo_Doi_Tuong_Lai'!$AE$2:$AE$1000, "<>CHỜ T+3"), 0) | H9: =IF(D9>0, E9/D9, 0) | I9: =IFERROR(AVERAGEIFS('2_Nhat_Ky_Theo_Doi_Tuong_Lai'!$AA$2:$AA$1000, '2_Nhat_Ky_Theo_Doi_Tuong_Lai'!$B$2:$B$1000, A9, '2_Nhat_Ky_Theo_Doi_Tuong_Lai'!$AF$2:$AF$1000, "THẮNG"), 0) | J9: =IFERROR(AVERAGEIFS('2_Nhat_Ky_Theo_Doi_Tuong_Lai'!$AA$2:$AA$1000, '2_Nhat_Ky_Theo_Doi_Tuong_Lai'!$B$2:$B$1000, A9, '2_Nhat_Ky_Theo_Doi_Tuong_Lai'!$AF$2:$AF$1000, "THUA"), 0) | K9: =IF(AND(F9>0, ABS(J9)>0), I9/ABS(J9), IF(E9>0, 5.0, 0)) | L9: =IF(ABS(SUMIFS('2_Nhat_Ky_Theo_Doi_Tuong_Lai'!$AA$2:$AA$1000, '2_Nhat_Ky_Theo_Doi_Tuong_Lai'!$B$2:$B$1000, A9, '2_Nhat_Ky_Theo_Doi_Tuong_Lai'!$AF$2:$AF$1000, "THUA"))>0, SUMIFS('2_Nhat_Ky_Theo_Doi_Tuong_Lai'!$AA$2:$AA$1000, '2_Nhat_Ky_Theo_Doi_Tuong_Lai'!$B$2:$B$1000, A9, '2_Nhat_Ky_Theo_Doi_Tuong_Lai'!$AF$2:$AF$1000, "THẮNG")/ABS(SUMIFS('2_Nhat_Ky_Theo_Doi_Tuong_Lai'!$AA$2:$AA$1000, '2_Nhat_Ky_Theo_Doi_Tuong_Lai'!$B$2:$B$1000, A9, '2_Nhat_Ky_Theo_Doi_Tuong_Lai'!$AF$2:$AF$1000, "THUA")), IF(E9>0, 5.0, 0)) | M9: =IF(D9>0, (H9*I9)+((1-H9)*J9), 0) | N9: =IFERROR(AVERAGEIFS('2_Nhat_Ky_Theo_Doi_Tuong_Lai'!$AB$2:$AB$1000, '2_Nhat_Ky_Theo_Doi_Tuong_Lai'!$B$2:$B$1000, A9, '2_Nhat_Ky_Theo_Doi_Tuong_Lai'!$AF$2:$AF$1000, "<>ĐANG CHỜ"), 0) | O9: =IF(D9=0, "⏳ Đang chờ T+1 -> T+3", IF(AND(M9>=0.015, L9>=1.5), "🏆 CHÉN THÁNH (Giải ngân Lớn)", IF(M9>0, "🟢 KỲ VỌNG DƯƠNG (Có Lợi Thế)", "🔴 KỲ VỌNG ÂM (Tạm Ngưng)")))
A10: ALGO_09 | B10: 🔄 BỘ 09: CHUYỂN PHA DÀI HẠN & VƯỢT MA200 (MA200 TURNAROUND) | C10: =COUNTIF('2_Nhat_Ky_Theo_Doi_Tuong_Lai'!$B$2:$B$1000, A10) | D10: =E10+F10 | E10: =COUNTIFS('2_Nhat_Ky_Theo_Doi_Tuong_Lai'!$B$2:$B$1000, A10, '2_Nhat_Ky_Theo_Doi_Tuong_Lai'!$AF$2:$AF$1000, "THẮNG") | F10: =COUNTIFS('2_Nhat_Ky_Theo_Doi_Tuong_Lai'!$B$2:$B$1000, A10, '2_Nhat_Ky_Theo_Doi_Tuong_Lai'!$AF$2:$AF$1000, "THUA") | G10: =IFERROR(COUNTIFS('2_Nhat_Ky_Theo_Doi_Tuong_Lai'!$B$2:$B$1000, A10, '2_Nhat_Ky_Theo_Doi_Tuong_Lai'!$AE$2:$AE$1000, "THẮNG")/COUNTIFS('2_Nhat_Ky_Theo_Doi_Tuong_Lai'!$B$2:$B$1000, A10, '2_Nhat_Ky_Theo_Doi_Tuong_Lai'!$AE$2:$AE$1000, "<>CHỜ T+3"), 0) | H10: =IF(D10>0, E10/D10, 0) | I10: =IFERROR(AVERAGEIFS('2_Nhat_Ky_Theo_Doi_Tuong_Lai'!$AA$2:$AA$1000, '2_Nhat_Ky_Theo_Doi_Tuong_Lai'!$B$2:$B$1000, A10, '2_Nhat_Ky_Theo_Doi_Tuong_Lai'!$AF$2:$AF$1000, "THẮNG"), 0) | J10: =IFERROR(AVERAGEIFS('2_Nhat_Ky_Theo_Doi_Tuong_Lai'!$AA$2:$AA$1000, '2_Nhat_Ky_Theo_Doi_Tuong_Lai'!$B$2:$B$1000, A10, '2_Nhat_Ky_Theo_Doi_Tuong_Lai'!$AF$2:$AF$1000, "THUA"), 0) | K10: =IF(AND(F10>0, ABS(J10)>0), I10/ABS(J10), IF(E10>0, 5.0, 0)) | L10: =IF(ABS(SUMIFS('2_Nhat_Ky_Theo_Doi_Tuong_Lai'!$AA$2:$AA$1000, '2_Nhat_Ky_Theo_Doi_Tuong_Lai'!$B$2:$B$1000, A10, '2_Nhat_Ky_Theo_Doi_Tuong_Lai'!$AF$2:$AF$1000, "THUA"))>0, SUMIFS('2_Nhat_Ky_Theo_Doi_Tuong_Lai'!$AA$2:$AA$1000, '2_Nhat_Ky_Theo_Doi_Tuong_Lai'!$B$2:$B$1000, A10, '2_Nhat_Ky_Theo_Doi_Tuong_Lai'!$AF$2:$AF$1000, "THẮNG")/ABS(SUMIFS('2_Nhat_Ky_Theo_Doi_Tuong_Lai'!$AA$2:$AA$1000, '2_Nhat_Ky_Theo_Doi_Tuong_Lai'!$B$2:$B$1000, A10, '2_Nhat_Ky_Theo_Doi_Tuong_Lai'!$AF$2:$AF$1000, "THUA")), IF(E10>0, 5.0, 0)) | M10: =IF(D10>0, (H10*I10)+((1-H10)*J10), 0) | N10: =IFERROR(AVERAGEIFS('2_Nhat_Ky_Theo_Doi_Tuong_Lai'!$AB$2:$AB$1000, '2_Nhat_Ky_Theo_Doi_Tuong_Lai'!$B$2:$B$1000, A10, '2_Nhat_Ky_Theo_Doi_Tuong_Lai'!$AF$2:$AF$1000, "<>ĐANG CHỜ"), 0) | O10: =IF(D10=0, "⏳ Đang chờ T+1 -> T+3", IF(AND(M10>=0.015, L10>=1.5), "🏆 CHÉN THÁNH (Giải ngân Lớn)", IF(M10>0, "🟢 KỲ VỌNG DƯƠNG (Có Lợi Thế)", "🔴 KỲ VỌNG ÂM (Tạm Ngưng)")))
A11: ALGO_10 | B11: 🚀 BỘ 10: SÓNG ĐẦU CƠ BETA CAO & DÒNG TIỀN NÓNG (HIGH-BETA) | C11: =COUNTIF('2_Nhat_Ky_Theo_Doi_Tuong_Lai'!$B$2:$B$1000, A11) | D11: =E11+F11 | E11: =COUNTIFS('2_Nhat_Ky_Theo_Doi_Tuong_Lai'!$B$2:$B$1000, A11, '2_Nhat_Ky_Theo_Doi_Tuong_Lai'!$AF$2:$AF$1000, "THẮNG") | F11: =COUNTIFS('2_Nhat_Ky_Theo_Doi_Tuong_Lai'!$B$2:$B$1000, A11, '2_Nhat_Ky_Theo_Doi_Tuong_Lai'!$AF$2:$AF$1000, "THUA") | G11: =IFERROR(COUNTIFS('2_Nhat_Ky_Theo_Doi_Tuong_Lai'!$B$2:$B$1000, A11, '2_Nhat_Ky_Theo_Doi_Tuong_Lai'!$AE$2:$AE$1000, "THẮNG")/COUNTIFS('2_Nhat_Ky_Theo_Doi_Tuong_Lai'!$B$2:$B$1000, A11, '2_Nhat_Ky_Theo_Doi_Tuong_Lai'!$AE$2:$AE$1000, "<>CHỜ T+3"), 0) | H11: =IF(D11>0, E11/D11, 0) | I11: =IFERROR(AVERAGEIFS('2_Nhat_Ky_Theo_Doi_Tuong_Lai'!$AA$2:$AA$1000, '2_Nhat_Ky_Theo_Doi_Tuong_Lai'!$B$2:$B$1000, A11, '2_Nhat_Ky_Theo_Doi_Tuong_Lai'!$AF$2:$AF$1000, "THẮNG"), 0) | J11: =IFERROR(AVERAGEIFS('2_Nhat_Ky_Theo_Doi_Tuong_Lai'!$AA$2:$AA$1000, '2_Nhat_Ky_Theo_Doi_Tuong_Lai'!$B$2:$B$1000, A11, '2_Nhat_Ky_Theo_Doi_Tuong_Lai'!$AF$2:$AF$1000, "THUA"), 0) | K11: =IF(AND(F11>0, ABS(J11)>0), I11/ABS(J11), IF(E11>0, 5.0, 0)) | L11: =IF(ABS(SUMIFS('2_Nhat_Ky_Theo_Doi_Tuong_Lai'!$AA$2:$AA$1000, '2_Nhat_Ky_Theo_Doi_Tuong_Lai'!$B$2:$B$1000, A11, '2_Nhat_Ky_Theo_Doi_Tuong_Lai'!$AF$2:$AF$1000, "THUA"))>0, SUMIFS('2_Nhat_Ky_Theo_Doi_Tuong_Lai'!$AA$2:$AA$1000, '2_Nhat_Ky_Theo_Doi_Tuong_Lai'!$B$2:$B$1000, A11, '2_Nhat_Ky_Theo_Doi_Tuong_Lai'!$AF$2:$AF$1000, "THẮNG")/ABS(SUMIFS('2_Nhat_Ky_Theo_Doi_Tuong_Lai'!$AA$2:$AA$1000, '2_Nhat_Ky_Theo_Doi_Tuong_Lai'!$B$2:$B$1000, A11, '2_Nhat_Ky_Theo_Doi_Tuong_Lai'!$AF$2:$AF$1000, "THUA")), IF(E11>0, 5.0, 0)) | M11: =IF(D11>0, (H11*I11)+((1-H11)*J11), 0) | N11: =IFERROR(AVERAGEIFS('2_Nhat_Ky_Theo_Doi_Tuong_Lai'!$AB$2:$AB$1000, '2_Nhat_Ky_Theo_Doi_Tuong_Lai'!$B$2:$B$1000, A11, '2_Nhat_Ky_Theo_Doi_Tuong_Lai'!$AF$2:$AF$1000, "<>ĐANG CHỜ"), 0) | O11: =IF(D11=0, "⏳ Đang chờ T+1 -> T+3", IF(AND(M11>=0.015, L11>=1.5), "🏆 CHÉN THÁNH (Giải ngân Lớn)", IF(M11>0, "🟢 KỲ VỌNG DƯƠNG (Có Lợi Thế)", "🔴 KỲ VỌNG ÂM (Tạm Ngưng)")))
A12: ALGO_11 | B12: 💎 BỘ 11: MUA SỚM TRONG NỀN TÍCH LŨY (GIL MORALES POCKET PIVOT) | C12: =COUNTIF('2_Nhat_Ky_Theo_Doi_Tuong_Lai'!$B$2:$B$1000, A12) | D12: =E12+F12 | E12: =COUNTIFS('2_Nhat_Ky_Theo_Doi_Tuong_Lai'!$B$2:$B$1000, A12, '2_Nhat_Ky_Theo_Doi_Tuong_Lai'!$AF$2:$AF$1000, "THẮNG") | F12: =COUNTIFS('2_Nhat_Ky_Theo_Doi_Tuong_Lai'!$B$2:$B$1000, A12, '2_Nhat_Ky_Theo_Doi_Tuong_Lai'!$AF$2:$AF$1000, "THUA") | G12: =IFERROR(COUNTIFS('2_Nhat_Ky_Theo_Doi_Tuong_Lai'!$B$2:$B$1000, A12, '2_Nhat_Ky_Theo_Doi_Tuong_Lai'!$AE$2:$AE$1000, "THẮNG")/COUNTIFS('2_Nhat_Ky_Theo_Doi_Tuong_Lai'!$B$2:$B$1000, A12, '2_Nhat_Ky_Theo_Doi_Tuong_Lai'!$AE$2:$AE$1000, "<>CHỜ T+3"), 0) | H12: =IF(D12>0, E12/D12, 0) | I12: =IFERROR(AVERAGEIFS('2_Nhat_Ky_Theo_Doi_Tuong_Lai'!$AA$2:$AA$1000, '2_Nhat_Ky_Theo_Doi_Tuong_Lai'!$B$2:$B$1000, A12, '2_Nhat_Ky_Theo_Doi_Tuong_Lai'!$AF$2:$AF$1000, "THẮNG"), 0) | J12: =IFERROR(AVERAGEIFS('2_Nhat_Ky_Theo_Doi_Tuong_Lai'!$AA$2:$AA$1000, '2_Nhat_Ky_Theo_Doi_Tuong_Lai'!$B$2:$B$1000, A12, '2_Nhat_Ky_Theo_Doi_Tuong_Lai'!$AF$2:$AF$1000, "THUA"), 0) | K12: =IF(AND(F12>0, ABS(J12)>0), I12/ABS(J12), IF(E12>0, 5.0, 0)) | L12: =IF(ABS(SUMIFS('2_Nhat_Ky_Theo_Doi_Tuong_Lai'!$AA$2:$AA$1000, '2_Nhat_Ky_Theo_Doi_Tuong_Lai'!$B$2:$B$1000, A12, '2_Nhat_Ky_Theo_Doi_Tuong_Lai'!$AF$2:$AF$1000, "THUA"))>0, SUMIFS('2_Nhat_Ky_Theo_Doi_Tuong_Lai'!$AA$2:$AA$1000, '2_Nhat_Ky_Theo_Doi_Tuong_Lai'!$B$2:$B$1000, A12, '2_Nhat_Ky_Theo_Doi_Tuong_Lai'!$AF$2:$AF$1000, "THẮNG")/ABS(SUMIFS('2_Nhat_Ky_Theo_Doi_Tuong_Lai'!$AA$2:$AA$1000, '2_Nhat_Ky_Theo_Doi_Tuong_Lai'!$B$2:$B$1000, A12, '2_Nhat_Ky_Theo_Doi_Tuong_Lai'!$AF$2:$AF$1000, "THUA")), IF(E12>0, 5.0, 0)) | M12: =IF(D12>0, (H12*I12)+((1-H12)*J12), 0) | N12: =IFERROR(AVERAGEIFS('2_Nhat_Ky_Theo_Doi_Tuong_Lai'!$AB$2:$AB$1000, '2_Nhat_Ky_Theo_Doi_Tuong_Lai'!$B$2:$B$1000, A12, '2_Nhat_Ky_Theo_Doi_Tuong_Lai'!$AF$2:$AF$1000, "<>ĐANG CHỜ"), 0) | O12: =IF(D12=0, "⏳ Đang chờ T+1 -> T+3", IF(AND(M12>=0.015, L12>=1.5), "🏆 CHÉN THÁNH (Giải ngân Lớn)", IF(M12>0, "🟢 KỲ VỌNG DƯƠNG (Có Lợi Thế)", "🔴 KỲ VỌNG ÂM (Tạm Ngưng)")))
A13: ALGO_12 | B13: 🏆 BỘ 12: MẪU HÌNH SIÊU CỔ PHIẾU SEPA (MINERVINI TREND TEMPLATE) | C13: =COUNTIF('2_Nhat_Ky_Theo_Doi_Tuong_Lai'!$B$2:$B$1000, A13) | D13: =E13+F13 | E13: =COUNTIFS('2_Nhat_Ky_Theo_Doi_Tuong_Lai'!$B$2:$B$1000, A13, '2_Nhat_Ky_Theo_Doi_Tuong_Lai'!$AF$2:$AF$1000, "THẮNG") | F13: =COUNTIFS('2_Nhat_Ky_Theo_Doi_Tuong_Lai'!$B$2:$B$1000, A13, '2_Nhat_Ky_Theo_Doi_Tuong_Lai'!$AF$2:$AF$1000, "THUA") | G13: =IFERROR(COUNTIFS('2_Nhat_Ky_Theo_Doi_Tuong_Lai'!$B$2:$B$1000, A13, '2_Nhat_Ky_Theo_Doi_Tuong_Lai'!$AE$2:$AE$1000, "THẮNG")/COUNTIFS('2_Nhat_Ky_Theo_Doi_Tuong_Lai'!$B$2:$B$1000, A13, '2_Nhat_Ky_Theo_Doi_Tuong_Lai'!$AE$2:$AE$1000, "<>CHỜ T+3"), 0) | H13: =IF(D13>0, E13/D13, 0) | I13: =IFERROR(AVERAGEIFS('2_Nhat_Ky_Theo_Doi_Tuong_Lai'!$AA$2:$AA$1000, '2_Nhat_Ky_Theo_Doi_Tuong_Lai'!$B$2:$B$1000, A13, '2_Nhat_Ky_Theo_Doi_Tuong_Lai'!$AF$2:$AF$1000, "THẮNG"), 0) | J13: =IFERROR(AVERAGEIFS('2_Nhat_Ky_Theo_Doi_Tuong_Lai'!$AA$2:$AA$1000, '2_Nhat_Ky_Theo_Doi_Tuong_Lai'!$B$2:$B$1000, A13, '2_Nhat_Ky_Theo_Doi_Tuong_Lai'!$AF$2:$AF$1000, "THUA"), 0) | K13: =IF(AND(F13>0, ABS(J13)>0), I13/ABS(J13), IF(E13>0, 5.0, 0)) | L13: =IF(ABS(SUMIFS('2_Nhat_Ky_Theo_Doi_Tuong_Lai'!$AA$2:$AA$1000, '2_Nhat_Ky_Theo_Doi_Tuong_Lai'!$B$2:$B$1000, A13, '2_Nhat_Ky_Theo_Doi_Tuong_Lai'!$AF$2:$AF$1000, "THUA"))>0, SUMIFS('2_Nhat_Ky_Theo_Doi_Tuong_Lai'!$AA$2:$AA$1000, '2_Nhat_Ky_Theo_Doi_Tuong_Lai'!$B$2:$B$1000, A13, '2_Nhat_Ky_Theo_Doi_Tuong_Lai'!$AF$2:$AF$1000, "THẮNG")/ABS(SUMIFS('2_Nhat_Ky_Theo_Doi_Tuong_Lai'!$AA$2:$AA$1000, '2_Nhat_Ky_Theo_Doi_Tuong_Lai'!$B$2:$B$1000, A13, '2_Nhat_Ky_Theo_Doi_Tuong_Lai'!$AF$2:$AF$1000, "THUA")), IF(E13>0, 5.0, 0)) | M13: =IF(D13>0, (H13*I13)+((1-H13)*J13), 0) | N13: =IFERROR(AVERAGEIFS('2_Nhat_Ky_Theo_Doi_Tuong_Lai'!$AB$2:$AB$1000, '2_Nhat_Ky_Theo_Doi_Tuong_Lai'!$B$2:$B$1000, A13, '2_Nhat_Ky_Theo_Doi_Tuong_Lai'!$AF$2:$AF$1000, "<>ĐANG CHỜ"), 0) | O13: =IF(D13=0, "⏳ Đang chờ T+1 -> T+3", IF(AND(M13>=0.015, L13>=1.5), "🏆 CHÉN THÁNH (Giải ngân Lớn)", IF(M13>0, "🟢 KỲ VỌNG DƯƠNG (Có Lợi Thế)", "🔴 KỲ VỌNG ÂM (Tạm Ngưng)")))
... A31: ALGO_30 | B31: 🌟 BỘ 30: ĐIỂM HỘI TỤ SIÊU ĐẲNG ĐA THUẬT TOÁN (MASTER CONFLUENCE) | C31: =COUNTIF('2_Nhat_Ky_Theo_Doi_Tuong_Lai'!$B$2:$B$1000, A31) | D31: =E31+F31 | E31: =COUNTIFS('2_Nhat_Ky_Theo_Doi_Tuong_Lai'!$B$2:$B$1000, A31, '2_Nhat_Ky_Theo_Doi_Tuong_Lai'!$AF$2:$AF$1000, "THẮNG") | F31: =COUNTIFS('2_Nhat_Ky_Theo_Doi_Tuong_Lai'!$B$2:$B$1000, A31, '2_Nhat_Ky_Theo_Doi_Tuong_Lai'!$AF$2:$AF$1000, "THUA") | G31: =IFERROR(COUNTIFS('2_Nhat_Ky_Theo_Doi_Tuong_Lai'!$B$2:$B$1000, A31, '2_Nhat_Ky_Theo_Doi_Tuong_Lai'!$AE$2:$AE$1000, "THẮNG")/COUNTIFS('2_Nhat_Ky_Theo_Doi_Tuong_Lai'!$B$2:$B$1000, A31, '2_Nhat_Ky_Theo_Doi_Tuong_Lai'!$AE$2:$AE$1000, "<>CHỜ T+3"), 0) | H31: =IF(D31>0, E31/D31, 0) | I31: =IFERROR(AVERAGEIFS('2_Nhat_Ky_Theo_Doi_Tuong_Lai'!$AA$2:$AA$1000, '2_Nhat_Ky_Theo_Doi_Tuong_Lai'!$B$2:$B$1000, A31, '2_Nhat_Ky_Theo_Doi_Tuong_Lai'!$AF$2:$AF$1000, "THẮNG"), 0) | J31: =IFERROR(AVERAGEIFS('2_Nhat_Ky_Theo_Doi_Tuong_Lai'!$AA$2:$AA$1000, '2_Nhat_Ky_Theo_Doi_Tuong_Lai'!$B$2:$B$1000, A31, '2_Nhat_Ky_Theo_Doi_Tuong_Lai'!$AF$2:$AF$1000, "THUA"), 0) | K31: =IF(AND(F31>0, ABS(J31)>0), I31/ABS(J31), IF(E31>0, 5.0, 0)) | L31: =IF(ABS(SUMIFS('2_Nhat_Ky_Theo_Doi_Tuong_Lai'!$AA$2:$AA$1000, '2_Nhat_Ky_Theo_Doi_Tuong_Lai'!$B$2:$B$1000, A31, '2_Nhat_Ky_Theo_Doi_Tuong_Lai'!$AF$2:$AF$1000, "THUA"))>0, SUMIFS('2_Nhat_Ky_Theo_Doi_Tuong_Lai'!$AA$2:$AA$1000, '2_Nhat_Ky_Theo_Doi_Tuong_Lai'!$B$2:$B$1000, A31, '2_Nhat_Ky_Theo_Doi_Tuong_Lai'!$AF$2:$AF$1000, "THẮNG")/ABS(SUMIFS('2_Nhat_Ky_Theo_Doi_Tuong_Lai'!$AA$2:$AA$1000, '2_Nhat_Ky_Theo_Doi_Tuong_Lai'!$B$2:$B$1000, A31, '2_Nhat_Ky_Theo_Doi_Tuong_Lai'!$AF$2:$AF$1000, "THUA")), IF(E31>0, 5.0, 0)) | M31: =IF(D31>0, (H31*I31)+((1-H31)*J31), 0) | N31: =IFERROR(AVERAGEIFS('2_Nhat_Ky_Theo_Doi_Tuong_Lai'!$AB$2:$AB$1000, '2_Nhat_Ky_Theo_Doi_Tuong_Lai'!$B$2:$B$1000, A31, '2_Nhat_Ky_Theo_Doi_Tuong_Lai'!$AF$2:$AF$1000, "<>ĐANG CHỜ"), 0) | O31: =IF(D31=0, "⏳ Đang chờ T+1 -> T+3", IF(AND(M31>=0.015, L31>=1.5), "🏆 CHÉN THÁNH (Giải ngân Lớn)", IF(M31>0, "🟢 KỲ VỌNG DƯƠNG (Có Lợi Thế)", "🔴 KỲ VỌNG ÂM (Tạm Ngưng)")))

Sheet 2_Nhat_Ky_Theo_Doi_Tuong_Lai
A1: Ngày Báo | B1: Mã Bộ | C1: Tên Bộ Thuật Toán | D1: Hạng | E1: Mã CP | F1: Sàn | G1: Nhóm Ngành | H1: Giá Mua (T+0) | I1: VNINDEX (T+0) | J1: Điểm Algo | K1: RVOL (T+0) | L1: Mục Tiêu Động (ATR) | M1: Cắt Lỗ Động (ATR) | N1: Giá Hiện Tại | O1: VNINDEX Hiện Tại | P1: Số Phiên GD (T+) | Q1: Đỉnh Cao Nhất (MFE) | R1: Đáy Thấp Nhất (MAE) | S1: Giá T+3 (Hàng Về) | T1: Giá T+5 (1 Tuần) | U1: Giá T+10 (2 Tuần) | V1: Giá T+20 (1 Tháng) | W1: Giá Chốt Lệnh (Khóa) | X1: Trạng Thái Lệnh | Y1: % Lãi/Lỗ T+3 (Ròng -0.4% phí) | Z1: % Lãi/Lỗ T+5 (Ròng -0.4% phí) | AA1: % Lãi/Lỗ Thực Tế (Sau Phí) | AB1: % Alpha vs VNINDEX | AC1: % Đỉnh MFE (Lãi Tối Đa) | AD1: % Đáy MAE (Sụt Giảm Tối Đa) | AE1: Kết Quả T+3 (Hàng Về) | AF1: Kết Quả Cuối Cùng | AG1: Link Ảnh Nến Cloud (T+0) | AH1: Ảnh Đồ Thị Nến Lúc Lọc (T+0)
A2: 2026-10-19 | B2: ALGO_01 | C2: 🔥 BỘ 01: BÙNG NỔ DÒNG TIỀN & VƯỢT NỀN (CANSLIM BREAKOUT) | D2: #1 | E2: VLB | F2: UPCOM | G2: Khai khoáng & VLXD | H2: 49.4 | I2: 1689.84 | J2: 90.47 | K2: 8.51 | L2: 52.92 | M2: 47.8 | N2: 49.3 | O2: 1689.62 | P2: 1 | Q2: 49.8 | R2: 47.8 | X2: ⏳ Chờ hàng về (T+1) | Y2: =IF(ISNUMBER(S2), ((S2-H2)/H2)-0.004, "") | Z2: =IF(ISNUMBER(T2), ((T2-H2)/H2)-0.004, "") | AA2: =IF(ISNUMBER(W2), ((W2-H2)/H2)-0.004, IF(P2>0, ((N2-H2)/H2)-0.004, 0)) | AB2: =IF(AND(ISNUMBER(I2), I2>0, ISNUMBER(O2), O2>0), AA2-((O2-I2)/I2), AA2) | AC2: =IF(ISNUMBER(Q2), (Q2-H2)/H2, 0) | AD2: =IF(ISNUMBER(R2), (R2-H2)/H2, 0) | AE2: =IF(ISNUMBER(Y2), IF(Y2>0, "THẮNG", "THUA"), "CHỜ T+3") | AF2: =IF(AND(P2=0, N2=H2, NOT(ISNUMBER(W2))), "ĐANG CHỜ", IF(AA2>0, "THẮNG", "THUA")) | AG2: https://quickchart.io/chart/render/zf-71f1a2c5-d194-4c34-b775-0ddbe74410d9 | AH2: =IF(AG2<>"", IMAGE(AG2, 1), "Chưa có ảnh")
A3: 2026-10-19 | B3: ALGO_01 | C3: 🔥 BỘ 01: BÙNG NỔ DÒNG TIỀN & VƯỢT NỀN (CANSLIM BREAKOUT) | D3: #2 | E3: PCB | F3: UPCOM | G3: Ngân hàng | H3: 9.5 | I3: 1689.84 | J3: 68.26 | K3: 2.33 | L3: 10.86 | M3: 8.88 | N3: 9.4 | O3: 1689.62 | P3: 1 | Q3: 9.7 | R3: 9 | X3: ⏳ Chờ hàng về (T+1) | Y3: =IF(ISNUMBER(S3), ((S3-H3)/H3)-0.004, "") | Z3: =IF(ISNUMBER(T3), ((T3-H3)/H3)-0.004, "") | AA3: =IF(ISNUMBER(W3), ((W3-H3)/H3)-0.004, IF(P3>0, ((N3-H3)/H3)-0.004, 0)) | AB3: =IF(AND(ISNUMBER(I3), I3>0, ISNUMBER(O3), O3>0), AA3-((O3-I3)/I3), AA3) | AC3: =IF(ISNUMBER(Q3), (Q3-H3)/H3, 0) | AD3: =IF(ISNUMBER(R3), (R3-H3)/H3, 0) | AE3: =IF(ISNUMBER(Y3), IF(Y3>0, "THẮNG", "THUA"), "CHỜ T+3") | AF3: =IF(AND(P3=0, N3=H3, NOT(ISNUMBER(W3))), "ĐANG CHỜ", IF(AA3>0, "THẮNG", "THUA")) | AG3: https://quickchart.io/chart/render/zf-4cd6ac07-54c7-47d5-849f-3946e7c29e24 | AH3: =IF(AG3<>"", IMAGE(AG3, 1), "Chưa có ảnh")
A4: 2026-10-19 | B4: ALGO_01 | C4: 🔥 BỘ 01: BÙNG NỔ DÒNG TIỀN & VƯỢT NỀN (CANSLIM BREAKOUT) | D4: #3 | E4: FRT | F4: HOSE | G4: Bán lẻ & Phân phối | H4: 146 | I4: 1689.84 | J4: 38.78 | K4: 1.76 | L4: 165.9 | M4: 136.95 | N4: 145.9 | O4: 1689.62 | P4: 1 | Q4: 146 | R4: 140 | X4: ⏳ Chờ hàng về (T+1) | Y4: =IF(ISNUMBER(S4), ((S4-H4)/H4)-0.004, "") | Z4: =IF(ISNUMBER(T4), ((T4-H4)/H4)-0.004, "") | AA4: =IF(ISNUMBER(W4), ((W4-H4)/H4)-0.004, IF(P4>0, ((N4-H4)/H4)-0.004, 0)) | AB4: =IF(AND(ISNUMBER(I4), I4>0, ISNUMBER(O4), O4>0), AA4-((O4-I4)/I4), AA4) | AC4: =IF(ISNUMBER(Q4), (Q4-H4)/H4, 0) | AD4: =IF(ISNUMBER(R4), (R4-H4)/H4, 0) | AE4: =IF(ISNUMBER(Y4), IF(Y4>0, "THẮNG", "THUA"), "CHỜ T+3") | AF4: =IF(AND(P4=0, N4=H4, NOT(ISNUMBER(W4))), "ĐANG CHỜ", IF(AA4>0, "THẮNG", "THUA")) | AG4: https://quickchart.io/chart/render/zf-11afd18c-418e-4b18-af9c-52de7623cf95 | AH4: =IF(AG4<>"", IMAGE(AG4, 1), "Chưa có ảnh")
A5: 2026-10-19 | B5: ALGO_02 | C5: 🛡️ BỘ 02: GOM NỀN TÍCH LŨY SIẾT BIÊN ĐỘ VCP (SEPA ACCUMULATION) | D5: #1 | E5: PET | F5: HOSE | G5: Dầu khí & Năng lượng | H5: 50 | I5: 1689.84 | J5: 55.99 | K5: 0.85 | L5: 57.15 | M5: 46.75 | N5: 50 | O5: 1689.62 | P5: 1 | Q5: 51 | R5: 49.85 | X5: ⏳ Chờ hàng về (T+1) | Y5: =IF(ISNUMBER(S5), ((S5-H5)/H5)-0.004, "") | Z5: =IF(ISNUMBER(T5), ((T5-H5)/H5)-0.004, "") | AA5: =IF(ISNUMBER(W5), ((W5-H5)/H5)-0.004, IF(P5>0, ((N5-H5)/H5)-0.004, 0)) | AB5: =IF(AND(ISNUMBER(I5), I5>0, ISNUMBER(O5), O5>0), AA5-((O5-I5)/I5), AA5) | AC5: =IF(ISNUMBER(Q5), (Q5-H5)/H5, 0) | AD5: =IF(ISNUMBER(R5), (R5-H5)/H5, 0) | AE5: =IF(ISNUMBER(Y5), IF(Y5>0, "THẮNG", "THUA"), "CHỜ T+3") | AF5: =IF(AND(P5=0, N5=H5, NOT(ISNUMBER(W5))), "ĐANG CHỜ", IF(AA5>0, "THẮNG", "THUA")) | AG5: https://quickchart.io/chart/render/zf-88792a7b-eebc-4f47-8af7-f28e30ec74af | AH5: =IF(AG5<>"", IMAGE(AG5, 1), "Chưa có ảnh")
A6: 2026-10-19 | B6: ALGO_02 | C6: 🛡️ BỘ 02: GOM NỀN TÍCH LŨY SIẾT BIÊN ĐỘ VCP (SEPA ACCUMULATION) | D6: #2 | E6: HSG | F6: HOSE | G6: Thép & VLXD | H6: 10.45 | I6: 1689.84 | J6: 31.29 | K6: 0.79 | L6: 11.4 | M6: 10.02 | N6: 10.55 | O6: 1689.62 | P6: 1 | Q6: 10.55 | R6: 10.35 | X6: ⏳ Chờ hàng về (T+1) | Y6: =IF(ISNUMBER(S6), ((S6-H6)/H6)-0.004, "") | Z6: =IF(ISNUMBER(T6), ((T6-H6)/H6)-0.004, "") | AA6: =IF(ISNUMBER(W6), ((W6-H6)/H6)-0.004, IF(P6>0, ((N6-H6)/H6)-0.004, 0)) | AB6: =IF(AND(ISNUMBER(I6), I6>0, ISNUMBER(O6), O6>0), AA6-((O6-I6)/I6), AA6) | AC6: =IF(ISNUMBER(Q6), (Q6-H6)/H6, 0) | AD6: =IF(ISNUMBER(R6), (R6-H6)/H6, 0) | AE6: =IF(ISNUMBER(Y6), IF(Y6>0, "THẮNG", "THUA"), "CHỜ T+3") | AF6: =IF(AND(P6=0, N6=H6, NOT(ISNUMBER(W6))), "ĐANG CHỜ", IF(AA6>0, "THẮNG", "THUA")) | AG6: https://quickchart.io/chart/render/zf-302cb06a-387f-46ab-9c38-666439666377 | AH6: =IF(AG6<>"", IMAGE(AG6, 1), "Chưa có ảnh")
A7: 2026-10-19 | B7: ALGO_02 | C7: 🛡️ BỘ 02: GOM NỀN TÍCH LŨY SIẾT BIÊN ĐỘ VCP (SEPA ACCUMULATION) | D7: #3 | E7: TLG | F7: HOSE | G7: Hàng tiêu dùng | H7: 55.7 | I7: 1689.84 | J7: 26.35 | K7: 0.85 | L7: 60.68 | M7: 53.43 | N7: 57 | O7: 1689.62 | P7: 1 | Q7: 57 | R7: 54.7 | X7: ⏳ Chờ hàng về (T+1) | Y7: =IF(ISNUMBER(S7), ((S7-H7)/H7)-0.004, "") | Z7: =IF(ISNUMBER(T7), ((T7-H7)/H7)-0.004, "") | AA7: =IF(ISNUMBER(W7), ((W7-H7)/H7)-0.004, IF(P7>0, ((N7-H7)/H7)-0.004, 0)) | AB7: =IF(AND(ISNUMBER(I7), I7>0, ISNUMBER(O7), O7>0), AA7-((O7-I7)/I7), AA7) | AC7: =IF(ISNUMBER(Q7), (Q7-H7)/H7, 0) | AD7: =IF(ISNUMBER(R7), (R7-H7)/H7, 0) | AE7: =IF(ISNUMBER(Y7), IF(Y7>0, "THẮNG", "THUA"), "CHỜ T+3") | AF7: =IF(AND(P7=0, N7=H7, NOT(ISNUMBER(W7))), "ĐANG CHỜ", IF(AA7>0, "THẮNG", "THUA")) | AG7: https://quickchart.io/chart/render/zf-a6459fd5-a6d0-48d8-921a-b21a2a492420 | AH7: =IF(AG7<>"", IMAGE(AG7, 1), "Chưa có ảnh")
A8: 2026-10-19 | B8: ALGO_02 | C8: 🛡️ BỘ 02: GOM NỀN TÍCH LŨY SIẾT BIÊN ĐỘ VCP (SEPA ACCUMULATION) | D8: #4 | E8: TVN | F8: UPCOM | G8: Thép & VLXD | H8: 9.7 | I8: 1689.84 | J8: 22.26 | K8: 0.78 | L8: 11.09 | M8: 9.07 | N8: 9.8 | O8: 1689.62 | P8: 1 | Q8: 9.8 | R8: 9.5 | X8: ⏳ Chờ hàng về (T+1) | Y8: =IF(ISNUMBER(S8), ((S8-H8)/H8)-0.004, "") | Z8: =IF(ISNUMBER(T8), ((T8-H8)/H8)-0.004, "") | AA8: =IF(ISNUMBER(W8), ((W8-H8)/H8)-0.004, IF(P8>0, ((N8-H8)/H8)-0.004, 0)) | AB8: =IF(AND(ISNUMBER(I8), I8>0, ISNUMBER(O8), O8>0), AA8-((O8-I8)/I8), AA8) | AC8: =IF(ISNUMBER(Q8), (Q8-H8)/H8, 0) | AD8: =IF(ISNUMBER(R8), (R8-H8)/H8, 0) | AE8: =IF(ISNUMBER(Y8), IF(Y8>0, "THẮNG", "THUA"), "CHỜ T+3") | AF8: =IF(AND(P8=0, N8=H8, NOT(ISNUMBER(W8))), "ĐANG CHỜ", IF(AA8>0, "THẮNG", "THUA")) | AG8: https://quickchart.io/chart/render/zf-524d51db-1f0c-41c7-8c00-5ffd84202c97 | AH8: =IF(AG8<>"", IMAGE(AG8, 1), "Chưa có ảnh")
A9: 2026-10-19 | B9: ALGO_02 | C9: 🛡️ BỘ 02: GOM NỀN TÍCH LŨY SIẾT BIÊN ĐỘ VCP (SEPA ACCUMULATION) | D9: #5 | E9: TCB | F9: HOSE | G9: Ngân hàng | H9: 33.25 | I9: 1689.84 | J9: 19.13 | K9: 0.93 | L9: 36.05 | M9: 31.98 | N9: 33.25 | O9: 1689.62 | P9: 1 | Q9: 33.5 | R9: 32.75 | X9: ⏳ Chờ hàng về (T+1) | Y9: =IF(ISNUMBER(S9), ((S9-H9)/H9)-0.004, "") | Z9: =IF(ISNUMBER(T9), ((T9-H9)/H9)-0.004, "") | AA9: =IF(ISNUMBER(W9), ((W9-H9)/H9)-0.004, IF(P9>0, ((N9-H9)/H9)-0.004, 0)) | AB9: =IF(AND(ISNUMBER(I9), I9>0, ISNUMBER(O9), O9>0), AA9-((O9-I9)/I9), AA9) | AC9: =IF(ISNUMBER(Q9), (Q9-H9)/H9, 0) | AD9: =IF(ISNUMBER(R9), (R9-H9)/H9, 0) | AE9: =IF(ISNUMBER(Y9), IF(Y9>0, "THẮNG", "THUA"), "CHỜ T+3") | AF9: =IF(AND(P9=0, N9=H9, NOT(ISNUMBER(W9))), "ĐANG CHỜ", IF(AA9>0, "THẮNG", "THUA")) | AG9: https://quickchart.io/chart/render/zf-11757050-0dd7-4828-918b-2895df5c09d6 | AH9: =IF(AG9<>"", IMAGE(AG9, 1), "Chưa có ảnh")
A10: 2026-10-19 | B10: ALGO_03 | C10: ⚡ BỘ 03: BẮT ĐÁY RÚT CHÂN & ĐẢO CHIỀU QUÁ BÁN (WYCKOFF SPRING) | D10: #1 | E10: POM | F10: UPCOM | G10: Thép & VLXD | H10: 3.3 | I10: 1689.84 | J10: 54.06 | K10: 2.11 | L10: 3.77 | M10: 3.09 | N10: 3.3 | O10: 1689.62 | P10: 1 | Q10: 3.4 | R10: 3 | X10: ⏳ Chờ hàng về (T+1) | Y10: =IF(ISNUMBER(S10), ((S10-H10)/H10)-0.004, "") | Z10: =IF(ISNUMBER(T10), ((T10-H10)/H10)-0.004, "") | AA10: =IF(ISNUMBER(W10), ((W10-H10)/H10)-0.004, IF(P10>0, ((N10-H10)/H10)-0.004, 0)) | AB10: =IF(AND(ISNUMBER(I10), I10>0, ISNUMBER(O10), O10>0), AA10-((O10-I10)/I10), AA10) | AC10: =IF(ISNUMBER(Q10), (Q10-H10)/H10, 0) | AD10: =IF(ISNUMBER(R10), (R10-H10)/H10, 0) | AE10: =IF(ISNUMBER(Y10), IF(Y10>0, "THẮNG", "THUA"), "CHỜ T+3") | AF10: =IF(AND(P10=0, N10=H10, NOT(ISNUMBER(W10))), "ĐANG CHỜ", IF(AA10>0, "THẮNG", "THUA")) | AG10: https://quickchart.io/chart/render/zf-cdaa2cf9-3890-4774-b2b8-eed2528ce3bb | AH10: =IF(AG10<>"", IMAGE(AG10, 1), "Chưa có ảnh")
A11: 2026-10-19 | B11: ALGO_03 | C11: ⚡ BỘ 03: BẮT ĐÁY RÚT CHÂN & ĐẢO CHIỀU QUÁ BÁN (WYCKOFF SPRING) | D11: #2 | E11: HUT | F11: HNX | G11: Đầu tư công & Xây dựng | H11: 12.3 | I11: 1689.84 | J11: 43.75 | K11: 2.66 | L11: 13.65 | M11: 11.69 | N11: 12.2 | O11: 1689.62 | P11: 1 | Q11: 12.3 | R11: 12.1 | X11: ⏳ Chờ hàng về (T+1) | Y11: =IF(ISNUMBER(S11), ((S11-H11)/H11)-0.004, "") | Z11: =IF(ISNUMBER(T11), ((T11-H11)/H11)-0.004, "") | AA11: =IF(ISNUMBER(W11), ((W11-H11)/H11)-0.004, IF(P11>0, ((N11-H11)/H11)-0.004, 0)) | AB11: =IF(AND(ISNUMBER(I11), I11>0, ISNUMBER(O11), O11>0), AA11-((O11-I11)/I11), AA11) | AC11: =IF(ISNUMBER(Q11), (Q11-H11)/H11, 0) | AD11: =IF(ISNUMBER(R11), (R11-H11)/H11, 0) | AE11: =IF(ISNUMBER(Y11), IF(Y11>0, "THẮNG", "THUA"), "CHỜ T+3") | AF11: =IF(AND(P11=0, N11=H11, NOT(ISNUMBER(W11))), "ĐANG CHỜ", IF(AA11>0, "THẮNG", "THUA")) | AG11: https://quickchart.io/chart/render/zf-07e82e16-615d-43f6-a7a0-2e584c60d96e | AH11: =IF(AG11<>"", IMAGE(AG11, 1), "Chưa có ảnh")
A12: 2026-10-19 | B12: ALGO_03 | C12: ⚡ BỘ 03: BẮT ĐÁY RÚT CHÂN & ĐẢO CHIỀU QUÁ BÁN (WYCKOFF SPRING) | D12: #3 | E12: VPL | F12: HOSE | G12: Dịch vụ Tiêu dùng | H12: 80 | I12: 1689.84 | J12: 28.26 | K12: 1.13 | L12: 89.17 | M12: 75.83 | N12: 79.3 | O12: 1689.62 | P12: 1 | Q12: 80 | R12: 78 | X12: ⏳ Chờ hàng về (T+1) | Y12: =IF(ISNUMBER(S12), ((S12-H12)/H12)-0.004, "") | Z12: =IF(ISNUMBER(T12), ((T12-H12)/H12)-0.004, "") | AA12: =IF(ISNUMBER(W12), ((W12-H12)/H12)-0.004, IF(P12>0, ((N12-H12)/H12)-0.004, 0)) | AB12: =IF(AND(ISNUMBER(I12), I12>0, ISNUMBER(O12), O12>0), AA12-((O12-I12)/I12), AA12) | AC12: =IF(ISNUMBER(Q12), (Q12-H12)/H12, 0) | AD12: =IF(ISNUMBER(R12), (R12-H12)/H12, 0) | AE12: =IF(ISNUMBER(Y12), IF(Y12>0, "THẮNG", "THUA"), "CHỜ T+3") | AF12: =IF(AND(P12=0, N12=H12, NOT(ISNUMBER(W12))), "ĐANG CHỜ", IF(AA12>0, "THẮNG", "THUA")) | AG12: https://quickchart.io/chart/render/zf-bc314b83-d3fc-40ae-8d06-cb7e1a9c832d | AH12: =IF(AG12<>"", IMAGE(AG12, 1), "Chưa có ảnh")
A13: 2026-10-19 | B13: ALGO_04 | C13: 👑 BỘ 04: SIÊU CỔ PHIẾU KHÁNG BÃO & ĐỈNH 52W (RS ALPHA LEADER) | D13: #1 | E13: BXH | F13: HNX | G13: Hóa chất & Chế biến | H13: 20 | I13: 1689.84 | J13: 224 | K13: 9.71 | L13: 22.86 | M13: 18.7 | N13: 20 | O13: 1689.62 | P13: 1 | Q13: 20 | R13: 20 | X13: ⏳ Chờ hàng về (T+1) | Y13: =IF(ISNUMBER(S13), ((S13-H13)/H13)-0.004, "") | Z13: =IF(ISNUMBER(T13), ((T13-H13)/H13)-0.004, "") | AA13: =IF(ISNUMBER(W13), ((W13-H13)/H13)-0.004, IF(P13>0, ((N13-H13)/H13)-0.004, 0)) | AB13: =IF(AND(ISNUMBER(I13), I13>0, ISNUMBER(O13), O13>0), AA13-((O13-I13)/I13), AA13) | AC13: =IF(ISNUMBER(Q13), (Q13-H13)/H13, 0) | AD13: =IF(ISNUMBER(R13), (R13-H13)/H13, 0) | AE13: =IF(ISNUMBER(Y13), IF(Y13>0, "THẮNG", "THUA"), "CHỜ T+3") | AF13: =IF(AND(P13=0, N13=H13, NOT(ISNUMBER(W13))), "ĐANG CHỜ", IF(AA13>0, "THẮNG", "THUA")) | AG13: https://quickchart.io/chart/render/zf-f37d8723-f43a-4646-ad2b-5d757c66aae5 | AH13: =IF(AG13<>"", IMAGE(AG13, 1), "Chưa có ảnh")
... A231: 2026-10-20 | B231: ALGO_30 | C231: 🌟 BỘ 30: ĐIỂM HỘI TỤ SIÊU ĐẲNG ĐA THUẬT TOÁN (MASTER CONFLUENCE) | D231: #5 | E231: CTD | F231: HOSE | G231: Đầu tư công & Xây dựng | H231: 65.2 | I231: 1689.62 | J231: 143.99 | K231: 5.02 | L231: 71.53 | M231: 62.32 | N231: 65.2 | O231: 1689.62 | P231: 0 | Q231: 65.2 | R231: 65.2 | X231: ⏳ Mới mua (T+0) | Y231: =IF(ISNUMBER(S231), ((S231-H231)/H231)-0.004, "") | Z231: =IF(ISNUMBER(T231), ((T231-H231)/H231)-0.004, "") | AA231: =IF(ISNUMBER(W231), ((W231-H231)/H231)-0.004, IF(P231>0, ((N231-H231)/H231)-0.004, 0)) | AB231: =IF(AND(ISNUMBER(I231), I231>0, ISNUMBER(O231), O231>0), AA231-((O231-I231)/I231), AA231) | AC231: =IF(ISNUMBER(Q231), (Q231-H231)/H231, 0) | AD231: =IF(ISNUMBER(R231), (R231-H231)/H231, 0) | AE231: =IF(ISNUMBER(Y231), IF(Y231>0, "THẮNG", "THUA"), "CHỜ T+3") | AF231: =IF(AND(P231=0, N231=H231, NOT(ISNUMBER(W231))), "ĐANG CHỜ", IF(AA231>0, "THẮNG", "THUA")) | AG231: https://quickchart.io/chart/render/zf-9d6b82f1-adac-4c7d-bf6e-0bc37d80d9e6 | AH231: =IF(AG231<>"", IMAGE(AG231, 1), "Chưa có ảnh")

Sheet 3_WinRate_Theo_Nhom_Nganh
A1: STT | B1: Tên Nhóm Ngành Chứng Khoán Việt Nam | C1: Tổng Tín Hiệu Ngành | D1: Số Lệnh Đã Phân Định | E1: Số Lệnh THẮNG | F1: Số Lệnh THUA | G1: Xác Suất Thắng Ngành (Win Rate %) | H1: Lãi/Lỗ Ròng Trung Bình (%) | I1: Alpha TB vs VNINDEX (%) | J1: Trạng Thái Dòng Tiền Ngành
A2: 1 | B2: Bán lẻ & Phân phối | C2: =COUNTIF('2_Nhat_Ky_Theo_Doi_Tuong_Lai'!$G$2:$G$1000, B2) | D2: =E2+F2 | E2: =COUNTIFS('2_Nhat_Ky_Theo_Doi_Tuong_Lai'!$G$2:$G$1000, B2, '2_Nhat_Ky_Theo_Doi_Tuong_Lai'!$AF$2:$AF$1000, "THẮNG") | F2: =COUNTIFS('2_Nhat_Ky_Theo_Doi_Tuong_Lai'!$G$2:$G$1000, B2, '2_Nhat_Ky_Theo_Doi_Tuong_Lai'!$AF$2:$AF$1000, "THUA") | G2: =IF(D2>0, E2/D2, 0) | H2: =IFERROR(AVERAGEIFS('2_Nhat_Ky_Theo_Doi_Tuong_Lai'!$AA$2:$AA$1000, '2_Nhat_Ky_Theo_Doi_Tuong_Lai'!$G$2:$G$1000, B2, '2_Nhat_Ky_Theo_Doi_Tuong_Lai'!$AF$2:$AF$1000, "<>ĐANG CHỜ"), 0) | I2: =IFERROR(AVERAGEIFS('2_Nhat_Ky_Theo_Doi_Tuong_Lai'!$AB$2:$AB$1000, '2_Nhat_Ky_Theo_Doi_Tuong_Lai'!$G$2:$G$1000, B2, '2_Nhat_Ky_Theo_Doi_Tuong_Lai'!$AF$2:$AF$1000, "<>ĐANG CHỜ"), 0) | J2: =IF(D2=0, "⏳ Đang theo dõi", IF(AND(G2>=0.60, H2>0.01), "🔥 NGÀNH DẪN SÓNG (Tỷ lệ ăn cao)", IF(H2>0, "🟢 Có sinh lời", "🩸 Dòng tiền yếu / Hay xịt")))
A3: 2 | B3: Bán lẻ & Tiêu dùng | C3: =COUNTIF('2_Nhat_Ky_Theo_Doi_Tuong_Lai'!$G$2:$G$1000, B3) | D3: =E3+F3 | E3: =COUNTIFS('2_Nhat_Ky_Theo_Doi_Tuong_Lai'!$G$2:$G$1000, B3, '2_Nhat_Ky_Theo_Doi_Tuong_Lai'!$AF$2:$AF$1000, "THẮNG") | F3: =COUNTIFS('2_Nhat_Ky_Theo_Doi_Tuong_Lai'!$G$2:$G$1000, B3, '2_Nhat_Ky_Theo_Doi_Tuong_Lai'!$AF$2:$AF$1000, "THUA") | G3: =IF(D3>0, E3/D3, 0) | H3: =IFERROR(AVERAGEIFS('2_Nhat_Ky_Theo_Doi_Tuong_Lai'!$AA$2:$AA$1000, '2_Nhat_Ky_Theo_Doi_Tuong_Lai'!$G$2:$G$1000, B3, '2_Nhat_Ky_Theo_Doi_Tuong_Lai'!$AF$2:$AF$1000, "<>ĐANG CHỜ"), 0) | I3: =IFERROR(AVERAGEIFS('2_Nhat_Ky_Theo_Doi_Tuong_Lai'!$AB$2:$AB$1000, '2_Nhat_Ky_Theo_Doi_Tuong_Lai'!$G$2:$G$1000, B3, '2_Nhat_Ky_Theo_Doi_Tuong_Lai'!$AF$2:$AF$1000, "<>ĐANG CHỜ"), 0) | J3: =IF(D3=0, "⏳ Đang theo dõi", IF(AND(G3>=0.60, H3>0.01), "🔥 NGÀNH DẪN SÓNG (Tỷ lệ ăn cao)", IF(H3>0, "🟢 Có sinh lời", "🩸 Dòng tiền yếu / Hay xịt")))
A4: 3 | B4: BĐS Khu Công Nghiệp | C4: =COUNTIF('2_Nhat_Ky_Theo_Doi_Tuong_Lai'!$G$2:$G$1000, B4) | D4: =E4+F4 | E4: =COUNTIFS('2_Nhat_Ky_Theo_Doi_Tuong_Lai'!$G$2:$G$1000, B4, '2_Nhat_Ky_Theo_Doi_Tuong_Lai'!$AF$2:$AF$1000, "THẮNG") | F4: =COUNTIFS('2_Nhat_Ky_Theo_Doi_Tuong_Lai'!$G$2:$G$1000, B4, '2_Nhat_Ky_Theo_Doi_Tuong_Lai'!$AF$2:$AF$1000, "THUA") | G4: =IF(D4>0, E4/D4, 0) | H4: =IFERROR(AVERAGEIFS('2_Nhat_Ky_Theo_Doi_Tuong_Lai'!$AA$2:$AA$1000, '2_Nhat_Ky_Theo_Doi_Tuong_Lai'!$G$2:$G$1000, B4, '2_Nhat_Ky_Theo_Doi_Tuong_Lai'!$AF$2:$AF$1000, "<>ĐANG CHỜ"), 0) | I4: =IFERROR(AVERAGEIFS('2_Nhat_Ky_Theo_Doi_Tuong_Lai'!$AB$2:$AB$1000, '2_Nhat_Ky_Theo_Doi_Tuong_Lai'!$G$2:$G$1000, B4, '2_Nhat_Ky_Theo_Doi_Tuong_Lai'!$AF$2:$AF$1000, "<>ĐANG CHỜ"), 0) | J4: =IF(D4=0, "⏳ Đang theo dõi", IF(AND(G4>=0.60, H4>0.01), "🔥 NGÀNH DẪN SÓNG (Tỷ lệ ăn cao)", IF(H4>0, "🟢 Có sinh lời", "🩸 Dòng tiền yếu / Hay xịt")))
A5: 4 | B5: Bất động sản Dân dụng | C5: =COUNTIF('2_Nhat_Ky_Theo_Doi_Tuong_Lai'!$G$2:$G$1000, B5) | D5: =E5+F5 | E5: =COUNTIFS('2_Nhat_Ky_Theo_Doi_Tuong_Lai'!$G$2:$G$1000, B5, '2_Nhat_Ky_Theo_Doi_Tuong_Lai'!$AF$2:$AF$1000, "THẮNG") | F5: =COUNTIFS('2_Nhat_Ky_Theo_Doi_Tuong_Lai'!$G$2:$G$1000, B5, '2_Nhat_Ky_Theo_Doi_Tuong_Lai'!$AF$2:$AF$1000, "THUA") | G5: =IF(D5>0, E5/D5, 0) | H5: =IFERROR(AVERAGEIFS('2_Nhat_Ky_Theo_Doi_Tuong_Lai'!$AA$2:$AA$1000, '2_Nhat_Ky_Theo_Doi_Tuong_Lai'!$G$2:$G$1000, B5, '2_Nhat_Ky_Theo_Doi_Tuong_Lai'!$AF$2:$AF$1000, "<>ĐANG CHỜ"), 0) | I5: =IFERROR(AVERAGEIFS('2_Nhat_Ky_Theo_Doi_Tuong_Lai'!$AB$2:$AB$1000, '2_Nhat_Ky_Theo_Doi_Tuong_Lai'!$G$2:$G$1000, B5, '2_Nhat_Ky_Theo_Doi_Tuong_Lai'!$AF$2:$AF$1000, "<>ĐANG CHỜ"), 0) | J5: =IF(D5=0, "⏳ Đang theo dõi", IF(AND(G5>=0.60, H5>0.01), "🔥 NGÀNH DẪN SÓNG (Tỷ lệ ăn cao)", IF(H5>0, "🟢 Có sinh lời", "🩸 Dòng tiền yếu / Hay xịt")))
A6: 5 | B6: Chứng khoán | C6: =COUNTIF('2_Nhat_Ky_Theo_Doi_Tuong_Lai'!$G$2:$G$1000, B6) | D6: =E6+F6 | E6: =COUNTIFS('2_Nhat_Ky_Theo_Doi_Tuong_Lai'!$G$2:$G$1000, B6, '2_Nhat_Ky_Theo_Doi_Tuong_Lai'!$AF$2:$AF$1000, "THẮNG") | F6: =COUNTIFS('2_Nhat_Ky_Theo_Doi_Tuong_Lai'!$G$2:$G$1000, B6, '2_Nhat_Ky_Theo_Doi_Tuong_Lai'!$AF$2:$AF$1000, "THUA") | G6: =IF(D6>0, E6/D6, 0) | H6: =IFERROR(AVERAGEIFS('2_Nhat_Ky_Theo_Doi_Tuong_Lai'!$AA$2:$AA$1000, '2_Nhat_Ky_Theo_Doi_Tuong_Lai'!$G$2:$G$1000, B6, '2_Nhat_Ky_Theo_Doi_Tuong_Lai'!$AF$2:$AF$1000, "<>ĐANG CHỜ"), 0) | I6: =IFERROR(AVERAGEIFS('2_Nhat_Ky_Theo_Doi_Tuong_Lai'!$AB$2:$AB$1000, '2_Nhat_Ky_Theo_Doi_Tuong_Lai'!$G$2:$G$1000, B6, '2_Nhat_Ky_Theo_Doi_Tuong_Lai'!$AF$2:$AF$1000, "<>ĐANG CHỜ"), 0) | J6: =IF(D6=0, "⏳ Đang theo dõi", IF(AND(G6>=0.60, H6>0.01), "🔥 NGÀNH DẪN SÓNG (Tỷ lệ ăn cao)", IF(H6>0, "🟢 Có sinh lời", "🩸 Dòng tiền yếu / Hay xịt")))
A7: 6 | B7: Công nghệ & Phần mềm | C7: =COUNTIF('2_Nhat_Ky_Theo_Doi_Tuong_Lai'!$G$2:$G$1000, B7) | D7: =E7+F7 | E7: =COUNTIFS('2_Nhat_Ky_Theo_Doi_Tuong_Lai'!$G$2:$G$1000, B7, '2_Nhat_Ky_Theo_Doi_Tuong_Lai'!$AF$2:$AF$1000, "THẮNG") | F7: =COUNTIFS('2_Nhat_Ky_Theo_Doi_Tuong_Lai'!$G$2:$G$1000, B7, '2_Nhat_Ky_Theo_Doi_Tuong_Lai'!$AF$2:$AF$1000, "THUA") | G7: =IF(D7>0, E7/D7, 0) | H7: =IFERROR(AVERAGEIFS('2_Nhat_Ky_Theo_Doi_Tuong_Lai'!$AA$2:$AA$1000, '2_Nhat_Ky_Theo_Doi_Tuong_Lai'!$G$2:$G$1000, B7, '2_Nhat_Ky_Theo_Doi_Tuong_Lai'!$AF$2:$AF$1000, "<>ĐANG CHỜ"), 0) | I7: =IFERROR(AVERAGEIFS('2_Nhat_Ky_Theo_Doi_Tuong_Lai'!$AB$2:$AB$1000, '2_Nhat_Ky_Theo_Doi_Tuong_Lai'!$G$2:$G$1000, B7, '2_Nhat_Ky_Theo_Doi_Tuong_Lai'!$AF$2:$AF$1000, "<>ĐANG CHỜ"), 0) | J7: =IF(D7=0, "⏳ Đang theo dõi", IF(AND(G7>=0.60, H7>0.01), "🔥 NGÀNH DẪN SÓNG (Tỷ lệ ăn cao)", IF(H7>0, "🟢 Có sinh lời", "🩸 Dòng tiền yếu / Hay xịt")))
A8: 7 | B8: Công nghệ & Viễn thông | C8: =COUNTIF('2_Nhat_Ky_Theo_Doi_Tuong_Lai'!$G$2:$G$1000, B8) | D8: =E8+F8 | E8: =COUNTIFS('2_Nhat_Ky_Theo_Doi_Tuong_Lai'!$G$2:$G$1000, B8, '2_Nhat_Ky_Theo_Doi_Tuong_Lai'!$AF$2:$AF$1000, "THẮNG") | F8: =COUNTIFS('2_Nhat_Ky_Theo_Doi_Tuong_Lai'!$G$2:$G$1000, B8, '2_Nhat_Ky_Theo_Doi_Tuong_Lai'!$AF$2:$AF$1000, "THUA") | G8: =IF(D8>0, E8/D8, 0) | H8: =IFERROR(AVERAGEIFS('2_Nhat_Ky_Theo_Doi_Tuong_Lai'!$AA$2:$AA$1000, '2_Nhat_Ky_Theo_Doi_Tuong_Lai'!$G$2:$G$1000, B8, '2_Nhat_Ky_Theo_Doi_Tuong_Lai'!$AF$2:$AF$1000, "<>ĐANG CHỜ"), 0) | I8: =IFERROR(AVERAGEIFS('2_Nhat_Ky_Theo_Doi_Tuong_Lai'!$AB$2:$AB$1000, '2_Nhat_Ky_Theo_Doi_Tuong_Lai'!$G$2:$G$1000, B8, '2_Nhat_Ky_Theo_Doi_Tuong_Lai'!$AF$2:$AF$1000, "<>ĐANG CHỜ"), 0) | J8: =IF(D8=0, "⏳ Đang theo dõi", IF(AND(G8>=0.60, H8>0.01), "🔥 NGÀNH DẪN SÓNG (Tỷ lệ ăn cao)", IF(H8>0, "🟢 Có sinh lời", "🩸 Dòng tiền yếu / Hay xịt")))
A9: 8 | B9: Cảng biển & Vận tải | C9: =COUNTIF('2_Nhat_Ky_Theo_Doi_Tuong_Lai'!$G$2:$G$1000, B9) | D9: =E9+F9 | E9: =COUNTIFS('2_Nhat_Ky_Theo_Doi_Tuong_Lai'!$G$2:$G$1000, B9, '2_Nhat_Ky_Theo_Doi_Tuong_Lai'!$AF$2:$AF$1000, "THẮNG") | F9: =COUNTIFS('2_Nhat_Ky_Theo_Doi_Tuong_Lai'!$G$2:$G$1000, B9, '2_Nhat_Ky_Theo_Doi_Tuong_Lai'!$AF$2:$AF$1000, "THUA") | G9: =IF(D9>0, E9/D9, 0) | H9: =IFERROR(AVERAGEIFS('2_Nhat_Ky_Theo_Doi_Tuong_Lai'!$AA$2:$AA$1000, '2_Nhat_Ky_Theo_Doi_Tuong_Lai'!$G$2:$G$1000, B9, '2_Nhat_Ky_Theo_Doi_Tuong_Lai'!$AF$2:$AF$1000, "<>ĐANG CHỜ"), 0) | I9: =IFERROR(AVERAGEIFS('2_Nhat_Ky_Theo_Doi_Tuong_Lai'!$AB$2:$AB$1000, '2_Nhat_Ky_Theo_Doi_Tuong_Lai'!$G$2:$G$1000, B9, '2_Nhat_Ky_Theo_Doi_Tuong_Lai'!$AF$2:$AF$1000, "<>ĐANG CHỜ"), 0) | J9: =IF(D9=0, "⏳ Đang theo dõi", IF(AND(G9>=0.60, H9>0.01), "🔥 NGÀNH DẪN SÓNG (Tỷ lệ ăn cao)", IF(H9>0, "🟢 Có sinh lời", "🩸 Dòng tiền yếu / Hay xịt")))
A10: 9 | B10: Dầu khí & Năng lượng | C10: =COUNTIF('2_Nhat_Ky_Theo_Doi_Tuong_Lai'!$G$2:$G$1000, B10) | D10: =E10+F10 | E10: =COUNTIFS('2_Nhat_Ky_Theo_Doi_Tuong_Lai'!$G$2:$G$1000, B10, '2_Nhat_Ky_Theo_Doi_Tuong_Lai'!$AF$2:$AF$1000, "THẮNG") | F10: =COUNTIFS('2_Nhat_Ky_Theo_Doi_Tuong_Lai'!$G$2:$G$1000, B10, '2_Nhat_Ky_Theo_Doi_Tuong_Lai'!$AF$2:$AF$1000, "THUA") | G10: =IF(D10>0, E10/D10, 0) | H10: =IFERROR(AVERAGEIFS('2_Nhat_Ky_Theo_Doi_Tuong_Lai'!$AA$2:$AA$1000, '2_Nhat_Ky_Theo_Doi_Tuong_Lai'!$G$2:$G$1000, B10, '2_Nhat_Ky_Theo_Doi_Tuong_Lai'!$AF$2:$AF$1000, "<>ĐANG CHỜ"), 0) | I10: =IFERROR(AVERAGEIFS('2_Nhat_Ky_Theo_Doi_Tuong_Lai'!$AB$2:$AB$1000, '2_Nhat_Ky_Theo_Doi_Tuong_Lai'!$G$2:$G$1000, B10, '2_Nhat_Ky_Theo_Doi_Tuong_Lai'!$AF$2:$AF$1000, "<>ĐANG CHỜ"), 0) | J10: =IF(D10=0, "⏳ Đang theo dõi", IF(AND(G10>=0.60, H10>0.01), "🔥 NGÀNH DẪN SÓNG (Tỷ lệ ăn cao)", IF(H10>0, "🟢 Có sinh lời", "🩸 Dòng tiền yếu / Hay xịt")))
A11: 10 | B11: Dịch vụ & Thương mại | C11: =COUNTIF('2_Nhat_Ky_Theo_Doi_Tuong_Lai'!$G$2:$G$1000, B11) | D11: =E11+F11 | E11: =COUNTIFS('2_Nhat_Ky_Theo_Doi_Tuong_Lai'!$G$2:$G$1000, B11, '2_Nhat_Ky_Theo_Doi_Tuong_Lai'!$AF$2:$AF$1000, "THẮNG") | F11: =COUNTIFS('2_Nhat_Ky_Theo_Doi_Tuong_Lai'!$G$2:$G$1000, B11, '2_Nhat_Ky_Theo_Doi_Tuong_Lai'!$AF$2:$AF$1000, "THUA") | G11: =IF(D11>0, E11/D11, 0) | H11: =IFERROR(AVERAGEIFS('2_Nhat_Ky_Theo_Doi_Tuong_Lai'!$AA$2:$AA$1000, '2_Nhat_Ky_Theo_Doi_Tuong_Lai'!$G$2:$G$1000, B11, '2_Nhat_Ky_Theo_Doi_Tuong_Lai'!$AF$2:$AF$1000, "<>ĐANG CHỜ"), 0) | I11: =IFERROR(AVERAGEIFS('2_Nhat_Ky_Theo_Doi_Tuong_Lai'!$AB$2:$AB$1000, '2_Nhat_Ky_Theo_Doi_Tuong_Lai'!$G$2:$G$1000, B11, '2_Nhat_Ky_Theo_Doi_Tuong_Lai'!$AF$2:$AF$1000, "<>ĐANG CHỜ"), 0) | J11: =IF(D11=0, "⏳ Đang theo dõi", IF(AND(G11>=0.60, H11>0.01), "🔥 NGÀNH DẪN SÓNG (Tỷ lệ ăn cao)", IF(H11>0, "🟢 Có sinh lời", "🩸 Dòng tiền yếu / Hay xịt")))
A12: 11 | B12: Dịch vụ Tiêu dùng | C12: =COUNTIF('2_Nhat_Ky_Theo_Doi_Tuong_Lai'!$G$2:$G$1000, B12) | D12: =E12+F12 | E12: =COUNTIFS('2_Nhat_Ky_Theo_Doi_Tuong_Lai'!$G$2:$G$1000, B12, '2_Nhat_Ky_Theo_Doi_Tuong_Lai'!$AF$2:$AF$1000, "THẮNG") | F12: =COUNTIFS('2_Nhat_Ky_Theo_Doi_Tuong_Lai'!$G$2:$G$1000, B12, '2_Nhat_Ky_Theo_Doi_Tuong_Lai'!$AF$2:$AF$1000, "THUA") | G12: =IF(D12>0, E12/D12, 0) | H12: =IFERROR(AVERAGEIFS('2_Nhat_Ky_Theo_Doi_Tuong_Lai'!$AA$2:$AA$1000, '2_Nhat_Ky_Theo_Doi_Tuong_Lai'!$G$2:$G$1000, B12, '2_Nhat_Ky_Theo_Doi_Tuong_Lai'!$AF$2:$AF$1000, "<>ĐANG CHỜ"), 0) | I12: =IFERROR(AVERAGEIFS('2_Nhat_Ky_Theo_Doi_Tuong_Lai'!$AB$2:$AB$1000, '2_Nhat_Ky_Theo_Doi_Tuong_Lai'!$G$2:$G$1000, B12, '2_Nhat_Ky_Theo_Doi_Tuong_Lai'!$AF$2:$AF$1000, "<>ĐANG CHỜ"), 0) | J12: =IF(D12=0, "⏳ Đang theo dõi", IF(AND(G12>=0.60, H12>0.01), "🔥 NGÀNH DẪN SÓNG (Tỷ lệ ăn cao)", IF(H12>0, "🟢 Có sinh lời", "🩸 Dòng tiền yếu / Hay xịt")))
A13: 12 | B13: Hàng tiêu dùng | C13: =COUNTIF('2_Nhat_Ky_Theo_Doi_Tuong_Lai'!$G$2:$G$1000, B13) | D13: =E13+F13 | E13: =COUNTIFS('2_Nhat_Ky_Theo_Doi_Tuong_Lai'!$G$2:$G$1000, B13, '2_Nhat_Ky_Theo_Doi_Tuong_Lai'!$AF$2:$AF$1000, "THẮNG") | F13: =COUNTIFS('2_Nhat_Ky_Theo_Doi_Tuong_Lai'!$G$2:$G$1000, B13, '2_Nhat_Ky_Theo_Doi_Tuong_Lai'!$AF$2:$AF$1000, "THUA") | G13: =IF(D13>0, E13/D13, 0) | H13: =IFERROR(AVERAGEIFS('2_Nhat_Ky_Theo_Doi_Tuong_Lai'!$AA$2:$AA$1000, '2_Nhat_Ky_Theo_Doi_Tuong_Lai'!$G$2:$G$1000, B13, '2_Nhat_Ky_Theo_Doi_Tuong_Lai'!$AF$2:$AF$1000, "<>ĐANG CHỜ"), 0) | I13: =IFERROR(AVERAGEIFS('2_Nhat_Ky_Theo_Doi_Tuong_Lai'!$AB$2:$AB$1000, '2_Nhat_Ky_Theo_Doi_Tuong_Lai'!$G$2:$G$1000, B13, '2_Nhat_Ky_Theo_Doi_Tuong_Lai'!$AF$2:$AF$1000, "<>ĐANG CHỜ"), 0) | J13: =IF(D13=0, "⏳ Đang theo dõi", IF(AND(G13>=0.60, H13>0.01), "🔥 NGÀNH DẪN SÓNG (Tỷ lệ ăn cao)", IF(H13>0, "🟢 Có sinh lời", "🩸 Dòng tiền yếu / Hay xịt")))
... A26: 25 | B26: Đầu tư công & Xây dựng | C26: =COUNTIF('2_Nhat_Ky_Theo_Doi_Tuong_Lai'!$G$2:$G$1000, B26) | D26: =E26+F26 | E26: =COUNTIFS('2_Nhat_Ky_Theo_Doi_Tuong_Lai'!$G$2:$G$1000, B26, '2_Nhat_Ky_Theo_Doi_Tuong_Lai'!$AF$2:$AF$1000, "THẮNG") | F26: =COUNTIFS('2_Nhat_Ky_Theo_Doi_Tuong_Lai'!$G$2:$G$1000, B26, '2_Nhat_Ky_Theo_Doi_Tuong_Lai'!$AF$2:$AF$1000, "THUA") | G26: =IF(D26>0, E26/D26, 0) | H26: =IFERROR(AVERAGEIFS('2_Nhat_Ky_Theo_Doi_Tuong_Lai'!$AA$2:$AA$1000, '2_Nhat_Ky_Theo_Doi_Tuong_Lai'!$G$2:$G$1000, B26, '2_Nhat_Ky_Theo_Doi_Tuong_Lai'!$AF$2:$AF$1000, "<>ĐANG CHỜ"), 0) | I26: =IFERROR(AVERAGEIFS('2_Nhat_Ky_Theo_Doi_Tuong_Lai'!$AB$2:$AB$1000, '2_Nhat_Ky_Theo_Doi_Tuong_Lai'!$G$2:$G$1000, B26, '2_Nhat_Ky_Theo_Doi_Tuong_Lai'!$AF$2:$AF$1000, "<>ĐANG CHỜ"), 0) | J26: =IF(D26=0, "⏳ Đang theo dõi", IF(AND(G26>=0.60, H26>0.01), "🔥 NGÀNH DẪN SÓNG (Tỷ lệ ăn cao)", IF(H26>0, "🟢 Có sinh lời", "🩸 Dòng tiền yếu / Hay xịt")))

Sheet 4_Du_Lieu_Toan_San_Hom_Nay
A1: ticker | B1: exchange | C1: sector | D1: cap_tier | E1: price | F1: val_billion | G1: r1d | H1: r5d | I1: r20d | J1: r60d | K1: rs_5d | L1: rvol | M1: rsi | N1: pe | O1: roe | P1: target_price | Q1: stop_price | R1: buy_zone | S1: is_bo_cung | T1: foreign_net_b | U1: confluence_count | V1: company
A2: TLG | B2: HOSE | C2: Hàng tiêu dùng | D2: Mid-Cap (Dòng tiền) | E2: 57 | F2: 6.90669 | G2: 2.3339318 | H2: 4.3956044 | I2: 7.1428571 | J2: 21.535181 | K2: 6.217822 | L2: 1.616205 | M2: 68.303428 | N2: 14.133376 | O2: 15.528994 | P2: 62.14 | Q2: 54.67 | R2: 🟢 VÙNG MUA CHUẨN | S2: FALSE | T2: 0 | U2: 13 | V2: CÔNG TY CỔ PHẦN TẬP ĐOÀN THIÊN LONG
A3: NT2 | B3: HOSE | C3: Dầu khí & Năng lượng | D3: Large-Cap (Bluechip) | E3: 24.2 | F3: 30.107849 | G3: 3.640257 | H3: 3.8626609 | I3: 17.761557 | J3: 11.520737 | K3: 5.6848785 | L3: 3.0215228 | M3: 76.403286 | N3: 5.8316437 | O3: 24.682994 | P3: 26.37 | Q3: 23.21 | R3: 🟢 VÙNG MUA CHUẨN | S3: FALSE | T3: 0 | U3: 12 | V3: CÔNG TY CỔ PHẦN ĐIỆN LỰC DẦU KHÍ NHƠN TRẠCH 2
A4: DHA | B4: HOSE | C4: Thép & VLXD | D4: Small-Cap (Penny) | E4: 56.6 | F4: 2.0304684 | G4: 3.2846715 | H4: 5.5970149 | I4: 4.8148148 | J4: 18.039625 | K4: 7.4192325 | L4: 5.1722572 | M4: 62.320314 | N4: 7.8447216 | O4: 21.500516 | P4: 63.41 | Q4: 53.5 | R4: 🟢 VÙNG MUA CHUẨN | S4: FALSE | T4: 0 | U4: 11 | V4: CÔNG TY CỔ PHẦN HÓA AN
A5: DDV | B5: UPCOM | C5: Hóa chất & Phân bón | D5: Mid-Cap (Dòng tiền) | E5: 17.9 | F5: 12.882129 | G5: 4.6783626 | H5: 6.547619 | I5: 5.2941176 | J5: -10.050251 | K5: 8.3698366 | L5: 3.379232 | M5: 60.41857 | N5: 0 | O5: 0 | P5: 20.4 | Q5: 16.77 | R5: 🟢 VÙNG MUA CHUẨN | S5: FALSE | T5: 0 | U5: 10 | V5: DAP-VINACHEM Joint Stock Co
A6: CTD | B6: HOSE | C6: Đầu tư công & Xây dựng | D6: Large-Cap (Bluechip) | E6: 65.2 | F6: 32.64251 | G6: 3.164557 | H6: 3.6565978 | I6: 10.884354 | J6: 11.835334 | K6: 5.4788153 | L6: 5.0238573 | M6: 67.565022 | N6: 9.0550266 | O6: 8.464105 | P6: 71.53 | Q6: 62.32 | R6: 🟢 VÙNG MUA CHUẨN | S6: FALSE | T6: 0 | U6: 10 | V6: CÔNG TY CỔ PHẦN XÂY DỰNG COTECCONS
A7: TNG | B7: HNX | C7: Thủy sản & Xuất khẩu | D7: Mid-Cap (Dòng tiền) | E7: 19.1 | F7: 18.711888 | G7: 3.2432432 | H7: 1.5957447 | I7: 17.177914 | J7: 13.017751 | K7: 3.4179623 | L7: 3.1783299 | M7: 65.022096 | N7: 5.5676035 | O7: 22.691107 | P7: 21.64 | Q7: 17.95 | R7: 🟢 VÙNG MUA CHUẨN | S7: FALSE | T7: 0 | U7: 9 | V7: TNG Investment and Trading JSC
A8: PAC | B8: HOSE | C8: Sản xuất Công nghiệp | D8: Mid-Cap (Dòng tiền) | E8: 15.35 | F8: 2.5512007 | G8: 4.0677966 | H8: 3.3670034 | I8: 6.9686411 | J8: -4.6583851 | K8: 5.1892209 | L8: 2.8808563 | M8: 61.436093 | N8: 13.443379 | O8: 8.5998398 | P8: 17.4 | Q8: 14.42 | R8: 🟢 VÙNG MUA CHUẨN | S8: FALSE | T8: 0 | U8: 9 | V8: CÔNG TY CỔ PHẦN PIN ẮC QUY MIỀN NAM
A9: ANV | B9: HOSE | C9: Thủy sản & Xuất khẩu | D9: Mid-Cap (Dòng tiền) | E9: 19.35 | F9: 8.9383068 | G9: 2.6525199 | H9: 5.7377049 | I9: 20.560748 | J9: 9.9431818 | K9: 7.5599225 | L9: 1.1554595 | M9: 66.790222 | N9: 5.9569762 | O9: 24.298995 | P9: 22.12 | Q9: 18.09 | R9: 🟢 VÙNG MUA CHUẨN | S9: FALSE | T9: 0 | U9: 7 | V9: CÔNG TY CỔ PHẦN NAM VIỆT
A10: DBC | B10: HOSE | C10: Hóa chất & Chế biến | D10: Mid-Cap (Dòng tiền) | E10: 15.95 | F10: 15.49632 | G10: 1.9169329 | H10: 5.2631579 | I10: -0.62111801 | J10: -2.7355623 | K10: 7.0853755 | L10: 1.9865606 | M10: 56.472757 | N10: 5.9535863 | O10: 14.347001 | P10: 17.44 | Q10: 15.27 | R10: 🟢 VÙNG MUA CHUẨN | S10: FALSE | T10: 0 | U10: 7 | V10: DABACO Group
A11: MSB | B11: HOSE | C11: Ngân hàng | D11: Large-Cap (Bluechip) | E11: 14.9 | F11: 22.471629 | G11: 0.67567568 | H11: 3.1034483 | I11: 15 | J11: 10.740741 | K11: 4.9256658 | L11: 0.34200227 | M11: 71.964295 | N11: 9.5320987 | O11: 13.931759 | P11: 16.24 | Q11: 14.29 | R11: 🟢 VÙNG MUA CHUẨN | S11: FALSE | T11: 0 | U11: 7 | V11: Vietnam Maritime Commercial Joint Stock Bank
A12: GMD | B12: HOSE | C12: Cảng biển & Vận tải | D12: Large-Cap (Bluechip) | E12: 54.9 | F12: 13.766889 | G12: 1.6666667 | H12: 2.2346369 | I12: 7.226562 | J12: 8.7846758 | K12: 4.0568544 | L12: 0.56589072 | M12: 64.334751 | N12: 14.996372 | O12: 18.046602 | P12: 60.11 | Q12: 52.53 | R12: 🟢 VÙNG MUA CHUẨN | S12: FALSE | T12: 0 | U12: 6 | V12: CÔNG TY CỔ PHẦN GEMADEPT
A13: VVS | B13: HOSE | C13: Bán lẻ & Phân phối | D13: Mid-Cap (Dòng tiền) | E13: 88.4 | F13: 9.6713136 | G13: 4.1224971 | H13: 9.9502488 | I13: 10.087173 | J13: -18.899083 | K13: 11.772466 | L13: 2.8215305 | M13: 58.459134 | N13: 0 | O13: 0 | P13: 100.95 | Q13: 82.69 | R13: 🟢 VÙNG MUA CHUẨN | S13: FALSE | T13: 0 | U13: 6 | V13: Vietnam Machine Investment Development Joint Stock Company
... A301: LAW | B301: UPCOM | C301: Đầu tư công & Xây dựng | D301: Micro / Kém TK | E301: 19.4 | F301: 0.00776 | G301: 0 | H301: 0 | I301: -25.096525 | J301: -21.774194 | K301: 1.8222176 | L301: 1.5844722 | M301: 43.878481 | N301: 0 | O301: 0 | P301: 22.17 | Q301: 18.14 | R301: 🟢 VÙNG MUA CHUẨN | S301: FALSE | T301: 0 | U301: 0 | V301: Long An Water Supply Sewerage Joint Stock Co
